[
  {
    "fecha": "2020-01-01",
    "indicativo": "3194U",
    "nombre": "MADRID, CIUDAD UNIVERSITARIA",
    "provincia": "MADRID",
    "altitud": "664",
    "tmed": "5,8",
    "prec": "0,0",
    "tmin": "-2,0",
    "horatmin": "07:50",
    "tmax": "13,7",
    "horatmax": "14:50",
    "hrMedia": "63",
    "hrMax": "88",
    "horaHrMax": "07:30",
    "hrMin": "38",
    "horaHrMin": "Varias",
    "pintMax": "0,0"
  },
  {
    "fecha": "2020-01-02",
    "indicativo": "3194U",
    "nombre": "MADRID, CIUDAD UNIVERSITARIA",
    "provincia": "MADRID",
    "altitud": "664",
    "tmed": "5,0",
    "prec": "0,0",
    "tmin": "-2,1",
    "horatmin": "08:30",
    "tmax": "12,1",
    "horatmax": "15:10",
    "hrMedia": "64",
    "hrMax": "87",
    "horaHrMax": "Varias",
    "hrMin": "40",
    "horaHrMin": "16:00",
    "pintMax": "0,0"
  },
  {
    "fecha": "2020-01-03",
    "indicativo": "3194U",
    "nombre": "MADRID, CIUDAD UNIVERSITARIA",
    "provincia": "MADRID",
    "altitud": "664",
    "tmed": "2,8",
    "prec": "0,0",
    "tmin": "-0,9",
    "horatmin": "05:40",
    "tmax": "6,6",
    "horatmax": "15:30",
    "hrMedia": "83",
    "hrMax": "87",
    "horaHrMax": "Varias",
    "hrMin": "69",
    "horaHrMin": "15:40",
    "pintMax": "0,0"
  },
  {
    "fecha": "2020-01-04",
    "indicativo": "3194U",
    "nombre": "MADRID, CIUDAD UNIVERSITARIA",
    "provincia": "MADRID",
    "altitud": "664",
    "tmed": "4,6",
    "prec": "0,0",
    "tmin": "-2,6",
    "horatmin": "08:00",
    "tmax": "11,8",
    "horatmax": "14:40",
    "hrMedia": "62",
    "hrMax": "88",
    "horaHrMax": "Varias",
    "hrMin": "39",
    "horaHrMin": "14:50",
    "pintMax": "0,0"
  },
  {
    "fecha": "2020-01-05",
    "indicativo": "3194U",
    "nombre": "MADRID, CIUDAD UNIVERSITARIA",
    "provincia": "MADRID",
    "altitud": "664",
    "tmed": "5,1",
    "prec": "0,0",
    "tmin": "-3,1",
    "horatmin": "08:00",
    "tmax": "13,3",
    "horatmax": "15:30",
    "hrMedia": "57",
    "hrMax": "85",
    "horaHrMax": "Varias",
    "hrMin": "32",
    "horaHrMin": "16:00",
    "pintMax": "0,0"
  },
  {
    "fecha": "2020-01-06",
    "indicativo": "3194U",
    "nombre": "MADRID, CIUDAD UNIVERSITARIA",
    "provincia": "MADRID",
    "altitud": "664",
    "tmed": "5,8",
    "prec": "0,0",
    "tmin": "-2,1",
    "horatmin": "08:00",
    "tmax": "13,7",
    "horatmax": "15:00",
    "hrMedia": "58",
    "hrMax": "87",
    "horaHrMax": "Varias",
    "hrMin": "32",
    "horaHrMin": "15:10",
    "pintMax": "0,0"
  },
  {
    "fecha": "2020-01-07",
    "indicativo": "3194U",
    "nombre": "MADRID, CIUDAD UNIVERSITARIA",
    "provincia": "MADRID",
    "altitud": "664",
    "tmed": "6,4",
    "prec": "0,0",
    "tmin": "-2,3",
    "horatmin": "08:00",
    "tmax": "15,1",
    "horatmax": "15:40",
    "hrMedia": "54",
    "hrMax": "87",
    "horaHrMax": "Varias",
    "hrMin": "28",
    "horaHrMin": "15:00",
    "pintMax": "0,0"
  },
  {
    "fecha": "2020-01-08",
    "indicativo": "3194U",
    "nombre": "MADRID, CIUDAD UNIVERSITARIA",
    "provincia": "MADRID",
    "altitud": "664",
    "tmed": "7,3",
    "prec": "0,0",
    "tmin": "-1,4",
    "horatmin": "05:40",
    "tmax": "16,0",
    "horatmax": "15:40",
    "hrMedia": "49",
    "hrMax": "87",
    "horaHrMax": "08:10",
    "hrMin": "24",
    "horaHrMin": "Varias",
    "pintMax": "0,0"
  },
  {
    "fecha": "2020-01-09",
    "indicativo": "3194U",
    "nombre": "MADRID, CIUDAD UNIVERSITARIA",
    "provincia": "MADRID",
    "altitud": "664",
    "tmed": "6,4",
    "prec": "0,0",
    "tmin": "0,0",
    "horatmin": "06:50",
    "tmax": "12,7",
    "horatmax": "14:30",
    "hrMedia": "59",
    "hrMax": "85",
    "horaHrMax": "07:40",
    "hrMin": "37",
    "horaHrMin": "13:00",
    "pintMax": "0,0"
  },
  {
    "fecha": "2020-01-10",
    "indicativo": "3194U",
    "nombre": "MADRID, CIUDAD UNIVERSITARIA",
    "provincia": "MADRID",
    "altitud": "664",
    "tmed": "6,2",
    "prec": "0,0",
    "tmin": "0,5",
    "horatmin": "08:10",
    "tmax": "12,0",
    "horatmax": "14:40",
    "hrMedia": "49",
    "hrMax": "83",
    "horaHrMax": "08:40",
    "hrMin": "30",
    "horaHrMin": "13:00",
    "pintMax": "0,0"
  },
  {
    "fecha": "2020-01-11",
    "indicativo": "3194U",
    "nombre": "MADRID, CIUDAD UNIVERSITARIA",
    "provincia": "MADRID",
    "altitud": "664",
    "tmed": "4,5",
    "prec": "0,0",
    "tmin": "-3,5",
    "horatmin": "08:20",
    "tmax": "12,5",
    "horatmax": "15:40",
    "hrMedia": "51",
    "hrMax": "84",
    "horaHrMax": "Varias",
    "hrMin": "27",
    "horaHrMin": "15:30",
    "pintMax": "0,0"
  },
  {
    "fecha": "2020-01-12",
    "indicativo": "3194U",
    "nombre": "MADRID, CIUDAD UNIVERSITARIA",
    "provincia": "MADRID",
    "altitud": "664",
    "tmed": "3,4",
    "prec": "0,0",
    "tmin": "-4,7",
    "horatmin": "07:50",
    "tmax": "11,6",
    "horatmax": "15:40",
    "hrMedia": "56",
    "hrMax": "85",
    "horaHrMax": "Varias",
    "hrMin": "29",
    "horaHrMin": "Varias",
    "pintMax": "0,0"
  },
  {
    "fecha": "2020-01-13",
    "indicativo": "3194U",
    "nombre": "MADRID, CIUDAD UNIVERSITARIA",
    "provincia": "MADRID",
    "altitud": "664",
    "tmed": "2,5",
    "prec": "0,0",
    "tmin": "-4,0",
    "horatmin": "07:40",
    "tmax": "9,0",
    "horatmax": "15:20",
    "hrMedia": "61",
    "hrMax": "87",
    "horaHrMax": "05:30",
    "hrMin": "43",
    "horaHrMin": "15:30",
    "pintMax": "0,0"
  },
  {
    "fecha": "2020-01-14",
    "indicativo": "3194U",
    "nombre": "MADRID, CIUDAD UNIVERSITARIA",
    "provincia": "MADRID",
    "altitud": "664",
    "tmed": "2,4",
    "prec": "0,0",
    "tmin": "-4,4",
    "horatmin": "08:00",
    "tmax": "9,2",
    "horatmax": "14:40",
    "hrMedia": "68",
    "hrMax": "87",
    "horaHrMax": "Varias",
    "hrMin": "48",
    "horaHrMin": "Varias",
    "pintMax": "0,0"
  },
  {
    "fecha": "2020-01-15",
    "indicativo": "3194U",
    "nombre": "MADRID, CIUDAD UNIVERSITARIA",
    "provincia": "MADRID",
    "altitud": "664",
    "tmed": "4,8",
    "prec": "0,0",
    "tmin": "1,4",
    "horatmin": "06:50",
    "tmax": "8,1",
    "horatmax": "15:50",
    "hrMedia": "75",
    "hrMax": "86",
    "horaHrMax": "Varias",
    "hrMin": "65",
    "horaHrMin": "14:50",
    "pintMax": "0,0"
  },
  {
    "fecha": "2020-01-16",
    "indicativo": "3194U",
    "nombre": "MADRID, CIUDAD UNIVERSITARIA",
    "provincia": "MADRID",
    "altitud": "664",
    "tmed": "9,8",
    "prec": "0,0",
    "tmin": "6,4",
    "horatmin": "02:00",
    "tmax": "13,2",
    "horatmax": "15:50",
    "hrMedia": "73",
    "hrMax": "79",
    "horaHrMax": "10:00",
    "hrMin": "49",
    "horaHrMin": "15:50",
    "pintMax": "0,0"
  },
  {
    "fecha": "2020-01-17",
    "indicativo": "3194U",
    "nombre": "MADRID, CIUDAD UNIVERSITARIA",
    "provincia": "MADRID",
    "altitud": "664",
    "tmed": "9,0",
    "prec": "0,5",
    "tmin": "4,7",
    "horatmin": "Varias",
    "tmax": "13,3",
    "horatmax": "15:20",
    "hrMedia": "66",
    "hrMax": "85",
    "horaHrMax": "08:40",
    "hrMin": "45",
    "horaHrMin": "14:10",
    "pintMax": "0,0"
  },
  {
    "fecha": "2020-01-18",
    "indicativo": "3194U",
    "nombre": "MADRID, CIUDAD UNIVERSITARIA",
    "provincia": "MADRID",
    "altitud": "664",
    "tmed": "5,8",
    "prec": "1,7",
    "tmin": "3,7",
    "horatmin": "03:00",
    "tmax": "8,0",
    "horatmax": "18:00",
    "hrMedia": "85",
    "hrMax": "87",
    "horaHrMax": "Varias",
    "hrMin": "76",
    "horaHrMin": "05:10",
    "pintMax": "1,8",
    "horaPIntMax": "22:05"
  },
  {
    "fecha": "2020-01-19",
    "indicativo": "3194U",
    "nombre": "MADRID, CIUDAD UNIVERSITARIA",
    "provincia": "MADRID",
    "altitud": "664",
    "tmed": "6,4",
    "prec": "0,1",
    "tmin": "1,8",
    "horatmin": "23:59",
    "tmax": "11,1",
    "horatmax": "14:00",
    "hrMedia": "48",
    "hrMax": "87",
    "horaHrMax": "Varias",
    "hrMin": "17",
    "horaHrMin": "16:20",
    "pintMax": "0,6",
    "horaPIntMax": "09:05"
  },
  {
    "fecha": "2020-01-20",
    "indicativo": "3194U",
    "nombre": "MADRID, CIUDAD UNIVERSITARIA",
    "provincia": "MADRID",
    "altitud": "664",
    "tmed": "3,8",
    "prec": "0,0",
    "tmin": "1,5",
    "horatmin": "00:30",
    "tmax": "6,1",
    "horatmax": "12:00",
    "hrMedia": "27",
    "hrMax": "44",
    "horaHrMax": "23:30",
    "hrMin": "22",
    "horaHrMin": "07:00",
    "pintMax": "0,0"
  },
  {
    "fecha": "2020-01-21",
    "indicativo": "3194U",
    "nombre": "MADRID, CIUDAD UNIVERSITARIA",
    "provincia": "MADRID",
    "altitud": "664",
    "tmed": "5,9",
    "prec": "3,4",
    "tmin": "4,0",
    "horatmin": "02:00",
    "tmax": "7,8",
    "horatmax": "13:50",
    "hrMedia": "58",
    "hrMax": "79",
    "horaHrMax": "16:10",
    "hrMin": "41",
    "horaHrMin": "00:00",
    "pintMax": "3,6",
    "horaPIntMax": "15:30"
  },
  {
    "fecha": "2020-01-22",
    "indicativo": "3194U",
    "nombre": "MADRID, CIUDAD UNIVERSITARIA",
    "provincia": "MADRID",
    "altitud": "664",
    "tmed": "7,2",
    "prec": "0,5",
    "tmin": "3,9",
    "horatmin": "23:59",
    "tmax": "10,4",
    "horatmax": "13:00",
    "hrMedia": "58",
    "hrMax": "77",
    "horaHrMax": "09:00",
    "hrMin": "50",
    "horaHrMin": "Varias",
    "pintMax": "0,6",
    "horaPIntMax": "Varias"
  },
  {
    "fecha": "2020-01-23",
    "indicativo": "3194U",
    "nombre": "MADRID, CIUDAD UNIVERSITARIA",
    "provincia": "MADRID",
    "altitud": "664",
    "tmed": "6,4",
    "prec": "1,2",
    "tmin": "2,4",
    "horatmin": "06:50",
    "tmax": "10,3",
    "horatmax": "15:00",
    "hrMedia": "62",
    "hrMax": "79",
    "horaHrMax": "06:40",
    "hrMin": "51",
    "horaHrMin": "Varias",
    "pintMax": "0,0"
  },
  {
    "fecha": "2020-01-24",
    "indicativo": "3194U",
    "nombre": "MADRID, CIUDAD UNIVERSITARIA",
    "provincia": "MADRID",
    "altitud": "664",
    "tmed": "7,4",
    "prec": "4,8",
    "tmin": "5,8",
    "horatmin": "22:00",
    "tmax": "9,0",
    "horatmax": "14:50",
    "hrMedia": "75",
    "hrMax": "84",
    "horaHrMax": "Varias",
    "hrMin": "66",
    "horaHrMin": "15:00",
    "pintMax": "1,2",
    "horaPIntMax": "Varias"
  },
  {
    "fecha": "2020-01-25",
    "indicativo": "3194U",
    "nombre": "MADRID, CIUDAD UNIVERSITARIA",
    "provincia": "MADRID",
    "altitud": "664",
    "tmed": "6,6",
    "prec": "5,6",
    "tmin": "4,6",
    "horatmin": "23:59",
    "tmax": "8,5",
    "horatmax": "12:30",
    "hrMedia": "83",
    "hrMax": "87",
    "horaHrMax": "Varias",
    "hrMin": "75",
    "horaHrMin": "11:10",
    "pintMax": "5,4",
    "horaPIntMax": "12:25"
  },
  {
    "fecha": "2020-01-26",
    "indicativo": "3194U",
    "nombre": "MADRID, CIUDAD UNIVERSITARIA",
    "provincia": "MADRID",
    "altitud": "664",
    "tmed": "6,8",
    "prec": "0,1",
    "tmin": "1,9",
    "horatmin": "07:30",
    "tmax": "11,7",
    "horatmax": "15:50",
    "hrMedia": "67",
    "hrMax": "88",
    "horaHrMax": "Varias",
    "hrMin": "44",
    "horaHrMin": "13:30",
    "pintMax": "0,6",
    "horaPIntMax": "07:15"
  },
  {
    "fecha": "2020-01-27",
    "indicativo": "3194U",
    "nombre": "MADRID, CIUDAD UNIVERSITARIA",
    "provincia": "MADRID",
    "altitud": "664",
    "tmed": "5,1",
    "prec": "0,3",
    "tmin": "1,9",
    "horatmin": "02:50",
    "tmax": "8,3",
    "horatmax": "17:00",
    "hrMedia": "80",
    "hrMax": "87",
    "horaHrMax": "Varias",
    "hrMin": "68",
    "horaHrMin": "18:00",
    "pintMax": "0,6",
    "horaPIntMax": "Varias"
  },
  {
    "fecha": "2020-01-28",
    "indicativo": "3194U",
    "nombre": "MADRID, CIUDAD UNIVERSITARIA",
    "provincia": "MADRID",
    "altitud": "664",
    "tmed": "10,4",
    "prec": "0,0",
    "tmin": "7,9",
    "horatmin": "00:10",
    "tmax": "12,8",
    "horatmax": "13:00",
    "hrMedia": "75",
    "hrMax": "85",
    "horaHrMax": "Varias",
    "hrMin": "68",
    "horaHrMin": "13:20",
    "pintMax": "0,0"
  },
  {
    "fecha": "2020-01-29",
    "indicativo": "3194U",
    "nombre": "MADRID, CIUDAD UNIVERSITARIA",
    "provincia": "MADRID",
    "altitud": "664",
    "tmed": "11,7",
    "prec": "0,0",
    "tmin": "9,5",
    "horatmin": "08:00",
    "tmax": "13,9",
    "horatmax": "13:30",
    "hrMedia": "71",
    "hrMax": "84",
    "horaHrMax": "Varias",
    "hrMin": "60",
    "horaHrMin": "13:30",
    "pintMax": "0,0"
  },
  {
    "fecha": "2020-01-30",
    "indicativo": "3194U",
    "nombre": "MADRID, CIUDAD UNIVERSITARIA",
    "provincia": "MADRID",
    "altitud": "664",
    "tmed": "10,0",
    "prec": "0,0",
    "tmin": "8,0",
    "horatmin": "07:10",
    "tmax": "12,0",
    "horatmax": "15:10",
    "hrMedia": "73",
    "hrMax": "85",
    "horaHrMax": "06:30",
    "hrMin": "59",
    "horaHrMin": "Varias",
    "pintMax": "0,0"
  },
  {
    "fecha": "2020-01-31",
    "indicativo": "3194U",
    "nombre": "MADRID, CIUDAD UNIVERSITARIA",
    "provincia": "MADRID",
    "altitud": "664",
    "tmed": "12,2",
    "prec": "0,1",
    "tmin": "8,9",
    "horatmin": "08:10",
    "tmax": "15,4",
    "horatmax": "15:00",
    "hrMedia": "70",
    "hrMax": "85",
    "horaHrMax": "Varias",
    "hrMin": "54",
    "horaHrMin": "15:00",
    "pintMax": "0,0"
  },
  {
    "fecha": "2020-02-01",
    "indicativo": "3194U",
    "nombre": "MADRID, CIUDAD UNIVERSITARIA",
    "provincia": "MADRID",
    "altitud": "664",
    "tmed": "14,4",
    "prec": "0,0",
    "tmin": "10,5",
    "horatmin": "23:00",
    "tmax": "18,2",
    "horatmax": "13:10",
    "hrMedia": "67",
    "hrMax": "86",
    "horaHrMax": "Varias",
    "hrMin": "48",
    "horaHrMin": "13:00",
    "pintMax": "0,6",
    "horaPIntMax": "02:35"
  },
  {
    "fecha": "2020-02-02",
    "indicativo": "3194U",
    "nombre": "MADRID, CIUDAD UNIVERSITARIA",
    "provincia": "MADRID",
    "altitud": "664",
    "tmed": "10,7",
    "prec": "0,0",
    "tmin": "9,2",
    "horatmin": "07:00",
    "tmax": "12,2",
    "horatmax": "15:30",
    "hrMedia": "78",
    "hrMax": "85",
    "horaHrMax": "Varias",
    "hrMin": "73",
    "horaHrMin": "17:10",
    "pintMax": "0,0"
  },
  {
    "fecha": "2020-02-03",
    "indicativo": "3194U",
    "nombre": "MADRID, CIUDAD UNIVERSITARIA",
    "provincia": "MADRID",
    "altitud": "664",
    "tmed": "13,4",
    "prec": "0,0",
    "tmin": "7,7",
    "horatmin": "07:50",
    "tmax": "19,2",
    "horatmax": "15:30",
    "hrMedia": "62",
    "hrMax": "85",
    "horaHrMax": "23:40",
    "hrMin": "34",
    "horaHrMin": "16:10",
    "pintMax": "0,0"
  },
  {
    "fecha": "2020-02-04",
    "indicativo": "3194U",
    "nombre": "MADRID, CIUDAD UNIVERSITARIA",
    "provincia": "MADRID",
    "altitud": "664",
    "tmed": "11,4",
    "prec": "0,0",
    "tmin": "3,4",
    "horatmin": "06:20",
    "tmax": "19,4",
    "horatmax": "15:30",
    "hrMedia": "58",
    "hrMax": "86",
    "horaHrMax": "Varias",
    "hrMin": "35",
    "horaHrMin": "16:30",
    "pintMax": "0,0"
  },
  {
    "fecha": "2020-02-05",
    "indicativo": "3194U",
    "nombre": "MADRID, CIUDAD UNIVERSITARIA",
    "provincia": "MADRID",
    "altitud": "664",
    "tmed": "7,9",
    "prec": "0,0",
    "tmin": "1,2",
    "horatmin": "07:30",
    "tmax": "14,6",
    "horatmax": "15:20",
    "hrMedia": "46",
    "hrMax": "79",
    "horaHrMax": "Varias",
    "hrMin": "25",
    "horaHrMin": "16:10",
    "pintMax": "0,0"
  },
  {
    "fecha": "2020-02-06",
    "indicativo": "3194U",
    "nombre": "MADRID, CIUDAD UNIVERSITARIA",
    "provincia": "MADRID",
    "altitud": "664",
    "tmed": "5,8",
    "prec": "0,0",
    "tmin": "0,8",
    "horatmin": "06:40",
    "tmax": "10,8",
    "horatmax": "14:50",
    "hrMedia": "74",
    "hrMax": "84",
    "horaHrMax": "Varias",
    "hrMin": "58",
    "horaHrMin": "14:40",
    "pintMax": "0,0"
  },
  {
    "fecha": "2020-02-07",
    "indicativo": "3194U",
    "nombre": "MADRID, CIUDAD UNIVERSITARIA",
    "provincia": "MADRID",
    "altitud": "664",
    "tmed": "7,4",
    "prec": "0,0",
    "tmin": "2,0",
    "horatmin": "07:00",
    "tmax": "12,7",
    "horatmax": "15:30",
    "hrMedia": "67",
    "hrMax": "87",
    "horaHrMax": "Varias",
    "hrMin": "50",
    "horaHrMin": "15:50",
    "pintMax": "0,0"
  },
  {
    "fecha": "2020-02-08",
    "indicativo": "3194U",
    "nombre": "MADRID, CIUDAD UNIVERSITARIA",
    "provincia": "MADRID",
    "altitud": "664",
    "tmed": "6,9",
    "prec": "0,0",
    "tmin": "3,1",
    "horatmin": "05:00",
    "tmax": "10,7",
    "horatmax": "17:00",
    "hrMedia": "75",
    "hrMax": "87",
    "horaHrMax": "04:40",
    "hrMin": "67",
    "horaHrMin": "16:40",
    "pintMax": "0,0"
  },
  {
    "fecha": "2020-02-09",
    "indicativo": "3194U",
    "nombre": "MADRID, CIUDAD UNIVERSITARIA",
    "provincia": "MADRID",
    "altitud": "664",
    "tmed": "8,4",
    "prec": "0,0",
    "tmin": "5,8",
    "horatmin": "07:40",
    "tmax": "10,9",
    "horatmax": "14:50",
    "hrMedia": "76",
    "hrMax": "86",
    "horaHrMax": "Varias",
    "hrMin": "66",
    "horaHrMin": "Varias",
    "pintMax": "0,0"
  },
  {
    "fecha": "2020-02-10",
    "indicativo": "3194U",
    "nombre": "MADRID, CIUDAD UNIVERSITARIA",
    "provincia": "MADRID",
    "altitud": "664",
    "tmed": "11,4",
    "prec": "0,0",
    "tmin": "6,1",
    "horatmin": "04:40",
    "tmax": "16,6",
    "horatmax": "15:50",
    "hrMedia": "67",
    "hrMax": "86",
    "horaHrMax": "Varias",
    "hrMin": "51",
    "horaHrMin": "Varias",
    "pintMax": "0,0"
  },
  {
    "fecha": "2020-02-11",
    "indicativo": "3194U",
    "nombre": "MADRID, CIUDAD UNIVERSITARIA",
    "provincia": "MADRID",
    "altitud": "664",
    "tmed": "8,6",
    "prec": "0,0",
    "tmin": "3,8",
    "horatmin": "04:50",
    "tmax": "13,5",
    "horatmax": "16:20",
    "hrMedia": "78",
    "hrMax": "86",
    "horaHrMax": "Varias",
    "hrMin": "57",
    "horaHrMin": "16:20",
    "pintMax": "0,0"
  },
  {
    "fecha": "2020-02-12",
    "indicativo": "3194U",
    "nombre": "MADRID, CIUDAD UNIVERSITARIA",
    "provincia": "MADRID",
    "altitud": "664",
    "tmed": "10,0",
    "prec": "0,0",
    "tmin": "8,6",
    "horatmin": "07:00",
    "tmax": "11,5",
    "horatmax": "13:40",
    "hrMedia": "77",
    "hrMax": "86",
    "horaHrMax": "Varias",
    "hrMin": "72",
    "horaHrMin": "Varias",
    "pintMax": "0,0"
  },
  {
    "fecha": "2020-02-13",
    "indicativo": "3194U",
    "nombre": "MADRID, CIUDAD UNIVERSITARIA",
    "provincia": "MADRID",
    "altitud": "664",
    "tmed": "10,4",
    "prec": "0,0",
    "tmin": "6,0",
    "horatmin": "23:59",
    "tmax": "14,9",
    "horatmax": "15:50",
    "hrMedia": "66",
    "hrMax": "84",
    "horaHrMax": "23:50",
    "hrMin": "49",
    "horaHrMin": "15:30",
    "pintMax": "0,0"
  },
  {
    "fecha": "2020-02-14",
    "indicativo": "3194U",
    "nombre": "MADRID, CIUDAD UNIVERSITARIA",
    "provincia": "MADRID",
    "altitud": "664",
    "tmed": "9,7",
    "prec": "0,0",
    "tmin": "4,3",
    "horatmin": "02:40",
    "tmax": "15,1",
    "horatmax": "16:10",
    "hrMedia": "67",
    "hrMax": "87",
    "horaHrMax": "Varias",
    "hrMin": "46",
    "horaHrMin": "15:50",
    "pintMax": "0,0"
  },
  {
    "fecha": "2020-02-15",
    "indicativo": "3194U",
    "nombre": "MADRID, CIUDAD UNIVERSITARIA",
    "provincia": "MADRID",
    "altitud": "664",
    "tmed": "8,8",
    "prec": "0,0",
    "tmin": "1,2",
    "horatmin": "06:50",
    "tmax": "16,3",
    "horatmax": "15:40",
    "hrMedia": "61",
    "hrMax": "86",
    "horaHrMax": "Varias",
    "hrMin": "41",
    "horaHrMin": "15:30",
    "pintMax": "0,0"
  },
  {
    "fecha": "2020-02-16",
    "indicativo": "3194U",
    "nombre": "MADRID, CIUDAD UNIVERSITARIA",
    "provincia": "MADRID",
    "altitud": "664",
    "tmed": "9,6",
    "prec": "0,0",
    "tmin": "1,8",
    "horatmin": "07:30",
    "tmax": "17,5",
    "horatmax": "15:40",
    "hrMedia": "58",
    "hrMax": "86",
    "horaHrMax": "09:10",
    "hrMin": "39",
    "horaHrMin": "17:10",
    "pintMax": "0,0"
  },
  {
    "fecha": "2020-02-17",
    "indicativo": "3194U",
    "nombre": "MADRID, CIUDAD UNIVERSITARIA",
    "provincia": "MADRID",
    "altitud": "664",
    "tmed": "9,7",
    "prec": "0,0",
    "tmin": "5,6",
    "horatmin": "02:50",
    "tmax": "13,8",
    "horatmax": "15:50",
    "hrMedia": "76",
    "hrMax": "85",
    "horaHrMax": "Varias",
    "hrMin": "60",
    "horaHrMin": "23:00",
    "pintMax": "0,0"
  },
  {
    "fecha": "2020-02-18",
    "indicativo": "3194U",
    "nombre": "MADRID, CIUDAD UNIVERSITARIA",
    "provincia": "MADRID",
    "altitud": "664",
    "tmed": "9,0",
    "prec": "0,0",
    "tmin": "4,2",
    "horatmin": "06:50",
    "tmax": "13,7",
    "horatmax": "17:00",
    "hrMedia": "55",
    "hrMax": "73",
    "horaHrMax": "01:10",
    "hrMin": "45",
    "horaHrMin": "15:30",
    "pintMax": "0,0"
  },
  {
    "fecha": "2020-02-19",
    "indicativo": "3194U",
    "nombre": "MADRID, CIUDAD UNIVERSITARIA",
    "provincia": "MADRID",
    "altitud": "664",
    "tmed": "8,0",
    "prec": "0,0",
    "tmin": "-0,3",
    "horatmin": "07:00",
    "tmax": "16,4",
    "horatmax": "16:10",
    "hrMedia": "47",
    "hrMax": "82",
    "horaHrMax": "07:20",
    "hrMin": "26",
    "horaHrMin": "16:10",
    "pintMax": "0,0"
  },
  {
    "fecha": "2020-02-20",
    "indicativo": "3194U",
    "nombre": "MADRID, CIUDAD UNIVERSITARIA",
    "provincia": "MADRID",
    "altitud": "664",
    "tmed": "8,5",
    "prec": "0,0",
    "tmin": "-0,9",
    "horatmin": "07:10",
    "tmax": "17,9",
    "horatmax": "16:10",
    "hrMedia": "48",
    "hrMax": "84",
    "horaHrMax": "Varias",
    "hrMin": "27",
    "horaHrMin": "15:50",
    "pintMax": "0,0"
  },
  {
    "fecha": "2020-02-21",
    "indicativo": "3194U",
    "nombre": "MADRID, CIUDAD UNIVERSITARIA",
    "provincia": "MADRID",
    "altitud": "664",
    "tmed": "10,4",
    "prec": "0,0",
    "tmin": "1,0",
    "horatmin": "07:10",
    "tmax": "19,7",
    "horatmax": "15:20",
    "hrMedia": "36",
    "hrMax": "74",
    "horaHrMax": "01:30",
    "hrMin": "19",
    "horaHrMin": "14:40",
    "pintMax": "0,0"
  },
  {
    "fecha": "2020-02-22",
    "indicativo": "3194U",
    "nombre": "MADRID, CIUDAD UNIVERSITARIA",
    "provincia": "MADRID",
    "altitud": "664",
    "tmed": "11,0",
    "prec": "0,0",
    "tmin": "0,3",
    "horatmin": "07:00",
    "tmax": "21,7",
    "horatmax": "17:00",
    "hrMedia": "40",
    "hrMax": "80",
    "horaHrMax": "07:40",
    "hrMin": "21",
    "horaHrMin": "Varias",
    "pintMax": "0,0"
  },
  {
    "fecha": "2020-02-23",
    "indicativo": "3194U",
    "nombre": "MADRID, CIUDAD UNIVERSITARIA",
    "provincia": "MADRID",
    "altitud": "664",
    "tmed": "11,6",
    "prec": "0,0",
    "tmin": "1,6",
    "horatmin": "07:30",
    "tmax": "21,5",
    "horatmax": "16:30",
    "hrMedia": "36",
    "hrMax": "68",
    "horaHrMax": "02:30",
    "hrMin": "21",
    "horaHrMin": "Varias",
    "pintMax": "0,0"
  },
  {
    "fecha": "2020-02-24",
    "indicativo": "3194U",
    "nombre": "MADRID, CIUDAD UNIVERSITARIA",
    "provincia": "MADRID",
    "altitud": "664",
    "tmed": "11,4",
    "prec": "0,0",
    "tmin": "1,4",
    "horatmin": "07:20",
    "tmax": "21,3",
    "horatmax": "15:10",
    "hrMedia": "43",
    "hrMax": "78",
    "horaHrMax": "06:50",
    "hrMin": "22",
    "horaHrMin": "15:10",
    "pintMax": "0,0"
  },
  {
    "fecha": "2020-02-25",
    "indicativo": "3194U",
    "nombre": "MADRID, CIUDAD UNIVERSITARIA",
    "provincia": "MADRID",
    "altitud": "664",
    "tmed": "10,4",
    "prec": "0,0",
    "tmin": "2,6",
    "horatmin": "04:30",
    "tmax": "18,2",
    "horatmax": "12:40",
    "hrMedia": "47",
    "hrMax": "72",
    "horaHrMax": "Varias",
    "hrMin": "23",
    "horaHrMin": "11:50",
    "pintMax": "0,0"
  },
  {
    "fecha": "2020-02-26",
    "indicativo": "3194U",
    "nombre": "MADRID, CIUDAD UNIVERSITARIA",
    "provincia": "MADRID",
    "altitud": "664",
    "tmed": "10,6",
    "prec": "0,0",
    "tmin": "5,0",
    "horatmin": "07:40",
    "tmax": "16,3",
    "horatmax": "15:10",
    "hrMedia": "42",
    "hrMax": "60",
    "horaHrMax": "07:30",
    "hrMin": "31",
    "horaHrMin": "15:40",
    "pintMax": "0,0"
  },
  {
    "fecha": "2020-02-27",
    "indicativo": "3194U",
    "nombre": "MADRID, CIUDAD UNIVERSITARIA",
    "provincia": "MADRID",
    "altitud": "664",
    "tmed": "12,4",
    "prec": "0,0",
    "tmin": "5,2",
    "horatmin": "05:50",
    "tmax": "19,5",
    "horatmax": "14:30",
    "hrMedia": "41",
    "hrMax": "66",
    "horaHrMax": "05:50",
    "hrMin": "29",
    "horaHrMin": "15:40",
    "pintMax": "0,0"
  },
  {
    "fecha": "2020-02-28",
    "indicativo": "3194U",
    "nombre": "MADRID, CIUDAD UNIVERSITARIA",
    "provincia": "MADRID",
    "altitud": "664",
    "tmed": "10,9",
    "prec": "0,0",
    "tmin": "2,9",
    "horatmin": "07:10",
    "tmax": "18,9",
    "horatmax": "15:20",
    "hrMedia": "45",
    "hrMax": "74",
    "horaHrMax": "07:30",
    "hrMin": "30",
    "horaHrMin": "Varias",
    "pintMax": "0,0"
  },
  {
    "fecha": "2020-02-29",
    "indicativo": "3194U",
    "nombre": "MADRID, CIUDAD UNIVERSITARIA",
    "provincia": "MADRID",
    "altitud": "664",
    "tmed": "9,4",
    "prec": "0,0",
    "tmin": "5,6",
    "horatmin": "00:30",
    "tmax": "13,2",
    "horatmax": "13:50",
    "hrMedia": "62",
    "hrMax": "81",
    "horaHrMax": "Varias",
    "hrMin": "54",
    "horaHrMin": "19:00",
    "pintMax": "0,0"
  },
  {
    "fecha": "2020-03-01",
    "indicativo": "3194U",
    "nombre": "MADRID, CIUDAD UNIVERSITARIA",
    "provincia": "MADRID",
    "altitud": "664",
    "tmed": "11,4",
    "prec": "3,2",
    "tmin": "7,5",
    "horatmin": "04:20",
    "tmax": "15,2",
    "horatmax": "15:50",
    "hrMedia": "71",
    "hrMax": "84",
    "horaHrMax": "Varias",
    "hrMin": "55",
    "horaHrMin": "15:50",
    "pintMax": "2,4",
    "horaPIntMax": "23:05"
  },
  {
    "fecha": "2020-03-02",
    "indicativo": "3194U",
    "nombre": "MADRID, CIUDAD UNIVERSITARIA",
    "provincia": "MADRID",
    "altitud": "664",
    "tmed": "9,2",
    "prec": "0,1",
    "tmin": "5,8",
    "horatmin": "23:50",
    "tmax": "12,5",
    "horatmax": "11:00",
    "hrMedia": "49",
    "hrMax": "86",
    "horaHrMax": "06:00",
    "hrMin": "32",
    "horaHrMin": "15:00",
    "pintMax": "1,8",
    "horaPIntMax": "05:45"
  },
  {
    "fecha": "2020-03-03",
    "indicativo": "3194U",
    "nombre": "MADRID, CIUDAD UNIVERSITARIA",
    "provincia": "MADRID",
    "altitud": "664",
    "tmed": "10,4",
    "prec": "0,0",
    "tmin": "5,1",
    "horatmin": "06:50",
    "tmax": "15,7",
    "horatmax": "16:00",
    "hrMedia": "63",
    "hrMax": "79",
    "horaHrMax": "23:00",
    "hrMin": "45",
    "horaHrMin": "00:00",
    "pintMax": "0,0"
  },
  {
    "fecha": "2020-03-04",
    "indicativo": "3194U",
    "nombre": "MADRID, CIUDAD UNIVERSITARIA",
    "provincia": "MADRID",
    "altitud": "664",
    "tmed": "14,3",
    "prec": "0,0",
    "tmin": "10,2",
    "horatmin": "06:50",
    "tmax": "18,4",
    "horatmax": "14:20",
    "hrMedia": "51",
    "hrMax": "84",
    "horaHrMax": "Varias",
    "hrMin": "33",
    "horaHrMin": "13:00",
    "pintMax": "0,0"
  },
  {
    "fecha": "2020-03-05",
    "indicativo": "3194U",
    "nombre": "MADRID, CIUDAD UNIVERSITARIA",
    "provincia": "MADRID",
    "altitud": "664",
    "tmed": "11,8",
    "prec": "0,2",
    "tmin": "7,2",
    "horatmin": "23:59",
    "tmax": "16,3",
    "horatmax": "13:40",
    "hrMedia": "47",
    "hrMax": "84",
    "horaHrMax": "05:00",
    "hrMin": "31",
    "horaHrMin": "Varias",
    "pintMax": "0,6",
    "horaPIntMax": "10:55"
  },
  {
    "fecha": "2020-03-06",
    "indicativo": "3194U",
    "nombre": "MADRID, CIUDAD UNIVERSITARIA",
    "provincia": "MADRID",
    "altitud": "664",
    "tmed": "8,4",
    "prec": "0,0",
    "tmin": "3,7",
    "horatmin": "23:59",
    "tmax": "13,0",
    "horatmax": "15:00",
    "hrMedia": "39",
    "hrMax": "57",
    "horaHrMax": "04:10",
    "hrMin": "28",
    "horaHrMin": "18:00",
    "pintMax": "0,6",
    "horaPIntMax": "03:55"
  },
  {
    "fecha": "2020-03-07",
    "indicativo": "3194U",
    "nombre": "MADRID, CIUDAD UNIVERSITARIA",
    "provincia": "MADRID",
    "altitud": "664",
    "tmed": "9,0",
    "prec": "0,0",
    "tmin": "1,5",
    "horatmin": "04:20",
    "tmax": "16,6",
    "horatmax": "15:40",
    "hrMedia": "43",
    "hrMax": "68",
    "horaHrMax": "23:59",
    "hrMin": "33",
    "horaHrMin": "15:40",
    "pintMax": "0,0"
  },
  {
    "fecha": "2020-03-08",
    "indicativo": "3194U",
    "nombre": "MADRID, CIUDAD UNIVERSITARIA",
    "provincia": "MADRID",
    "altitud": "664",
    "tmed": "7,0",
    "prec": "0,0",
    "tmin": "-1,0",
    "horatmin": "07:00",
    "tmax": "15,0",
    "horatmax": "13:20",
    "hrMedia": "54",
    "hrMax": "86",
    "horaHrMax": "07:20",
    "hrMin": "34",
    "horaHrMin": "13:00",
    "pintMax": "0,0"
  },
  {
    "fecha": "2020-03-09",
    "indicativo": "3194U",
    "nombre": "MADRID, CIUDAD UNIVERSITARIA",
    "provincia": "MADRID",
    "altitud": "664",
    "tmed": "12,1",
    "prec": "0,0",
    "tmin": "5,7",
    "horatmin": "07:20",
    "tmax": "18,5",
    "horatmax": "16:00",
    "hrMedia": "40",
    "hrMax": "63",
    "horaHrMax": "07:30",
    "hrMin": "29",
    "horaHrMin": "Varias",
    "pintMax": "0,0"
  },
  {
    "fecha": "2020-03-10",
    "indicativo": "3194U",
    "nombre": "MADRID, CIUDAD UNIVERSITARIA",
    "provincia": "MADRID",
    "altitud": "664",
    "tmed": "13,4",
    "prec": "0,0",
    "tmin": "3,9",
    "horatmin": "06:00",
    "tmax": "22,8",
    "horatmax": "16:00",
    "hrMedia": "43",
    "hrMax": "71",
    "horaHrMax": "06:30",
    "hrMin": "28",
    "horaHrMin": "18:00",
    "pintMax": "0,0"
  },
  {
    "fecha": "2020-03-11",
    "indicativo": "3194U",
    "nombre": "MADRID, CIUDAD UNIVERSITARIA",
    "provincia": "MADRID",
    "altitud": "664",
    "tmed": "14,8",
    "prec": "0,0",
    "tmin": "5,3",
    "horatmin": "07:00",
    "tmax": "24,3",
    "horatmax": "15:00",
    "hrMedia": "47",
    "hrMax": "81",
    "horaHrMax": "Varias",
    "hrMin": "28",
    "horaHrMin": "14:50",
    "pintMax": "0,0"
  },
  {
    "fecha": "2020-03-12",
    "indicativo": "3194U",
    "nombre": "MADRID, CIUDAD UNIVERSITARIA",
    "provincia": "MADRID",
    "altitud": "664",
    "tmed": "15,6",
    "prec": "0,0",
    "tmin": "7,4",
    "horatmin": "06:40",
    "tmax": "23,7",
    "horatmax": "15:20",
    "hrMedia": "46",
    "hrMax": "82",
    "horaHrMax": "Varias",
    "hrMin": "26",
    "horaHrMin": "15:10",
    "pintMax": "0,0"
  },
  {
    "fecha": "2020-03-13",
    "indicativo": "3194U",
    "nombre": "MADRID, CIUDAD UNIVERSITARIA",
    "provincia": "MADRID",
    "altitud": "664",
    "tmed": "15,6",
    "prec": "0,0",
    "tmin": "8,2",
    "horatmin": "06:50",
    "tmax": "22,9",
    "horatmax": "16:10",
    "hrMedia": "46",
    "hrMax": "75",
    "horaHrMax": "06:50",
    "hrMin": "30",
    "horaHrMin": "Varias",
    "pintMax": "0,0"
  },
  {
    "fecha": "2020-03-14",
    "indicativo": "3194U",
    "nombre": "MADRID, CIUDAD UNIVERSITARIA",
    "provincia": "MADRID",
    "altitud": "664",
    "tmed": "14,4",
    "prec": "0,0",
    "tmin": "6,7",
    "horatmin": "06:50",
    "tmax": "22,2",
    "horatmax": "14:50",
    "hrMedia": "47",
    "hrMax": "79",
    "horaHrMax": "07:20",
    "hrMin": "26",
    "horaHrMin": "16:20",
    "pintMax": "0,0"
  },
  {
    "fecha": "2020-03-15",
    "indicativo": "3194U",
    "nombre": "MADRID, CIUDAD UNIVERSITARIA",
    "provincia": "MADRID",
    "altitud": "664",
    "tmed": "12,6",
    "prec": "1,8",
    "tmin": "5,8",
    "horatmin": "06:40",
    "tmax": "19,5",
    "horatmax": "16:00",
    "hrMedia": "52",
    "hrMax": "84",
    "horaHrMax": "20:00",
    "hrMin": "43",
    "horaHrMin": "13:00",
    "pintMax": "4,8",
    "horaPIntMax": "18:25"
  },
  {
    "fecha": "2020-03-16",
    "indicativo": "3194U",
    "nombre": "MADRID, CIUDAD UNIVERSITARIA",
    "provincia": "MADRID",
    "altitud": "664",
    "tmed": "6,6",
    "prec": "5,6",
    "tmin": "3,2",
    "horatmin": "07:00",
    "tmax": "9,9",
    "horatmax": "00:10",
    "hrMedia": "68",
    "hrMax": "84",
    "horaHrMax": "Varias",
    "hrMin": "55",
    "horaHrMin": "10:10",
    "pintMax": "7,2",
    "horaPIntMax": "14:05"
  },
  {
    "fecha": "2020-03-17",
    "indicativo": "3194U",
    "nombre": "MADRID, CIUDAD UNIVERSITARIA",
    "provincia": "MADRID",
    "altitud": "664",
    "tmed": "10,5",
    "prec": "0,4",
    "tmin": "4,4",
    "horatmin": "01:40",
    "tmax": "16,6",
    "horatmax": "15:20",
    "hrMedia": "61",
    "hrMax": "87",
    "horaHrMax": "Varias",
    "hrMin": "42",
    "horaHrMin": "15:30",
    "pintMax": "1,8",
    "horaPIntMax": "06:15"
  },
  {
    "fecha": "2020-03-18",
    "indicativo": "3194U",
    "nombre": "MADRID, CIUDAD UNIVERSITARIA",
    "provincia": "MADRID",
    "altitud": "664",
    "tmed": "13,1",
    "prec": "0,0",
    "tmin": "9,6",
    "horatmin": "Varias",
    "tmax": "16,6",
    "horatmax": "14:20",
    "hrMedia": "52",
    "hrMax": "72",
    "horaHrMax": "Varias",
    "hrMin": "42",
    "horaHrMin": "13:30",
    "pintMax": "0,0"
  },
  {
    "fecha": "2020-03-19",
    "indicativo": "3194U",
    "nombre": "MADRID, CIUDAD UNIVERSITARIA",
    "provincia": "MADRID",
    "altitud": "664",
    "tmed": "12,8",
    "prec": "0,0",
    "tmin": "8,8",
    "horatmin": "04:10",
    "tmax": "16,7",
    "horatmax": "14:40",
    "hrMedia": "50",
    "hrMax": "77",
    "horaHrMax": "04:00",
    "hrMin": "38",
    "horaHrMin": "13:00",
    "pintMax": "0,0"
  },
  {
    "fecha": "2020-03-20",
    "indicativo": "3194U",
    "nombre": "MADRID, CIUDAD UNIVERSITARIA",
    "provincia": "MADRID",
    "altitud": "664",
    "tmed": "10,8",
    "prec": "0,0",
    "tmin": "9,3",
    "horatmin": "22:30",
    "tmax": "12,4",
    "horatmax": "14:40",
    "hrMedia": "56",
    "hrMax": "67",
    "horaHrMax": "22:20",
    "hrMin": "53",
    "horaHrMin": "18:00",
    "pintMax": "0,0"
  },
  {
    "fecha": "2020-03-21",
    "indicativo": "3194U",
    "nombre": "MADRID, CIUDAD UNIVERSITARIA",
    "provincia": "MADRID",
    "altitud": "664",
    "tmed": "8,4",
    "prec": "1,7",
    "tmin": "7,2",
    "horatmin": "23:59",
    "tmax": "9,7",
    "horatmax": "00:10",
    "hrMedia": "76",
    "hrMax": "83",
    "horaHrMax": "Varias",
    "hrMin": "64",
    "horaHrMin": "04:30",
    "pintMax": "2,4",
    "horaPIntMax": "12:05"
  },
  {
    "fecha": "2020-03-22",
    "indicativo": "3194U",
    "nombre": "MADRID, CIUDAD UNIVERSITARIA",
    "provincia": "MADRID",
    "altitud": "664",
    "tmed": "8,8",
    "prec": "7,3",
    "tmin": "5,5",
    "horatmin": "07:00",
    "tmax": "12,2",
    "horatmax": "15:00",
    "hrMedia": "65",
    "hrMax": "86",
    "horaHrMax": "23:50",
    "hrMin": "51",
    "horaHrMin": "16:00",
    "pintMax": "3,6",
    "horaPIntMax": "21:45"
  },
  {
    "fecha": "2020-03-23",
    "indicativo": "3194U",
    "nombre": "MADRID, CIUDAD UNIVERSITARIA",
    "provincia": "MADRID",
    "altitud": "664",
    "tmed": "10,9",
    "prec": "6,0",
    "tmin": "7,3",
    "horatmin": "06:50",
    "tmax": "14,5",
    "horatmax": "14:50",
    "hrMedia": "65",
    "hrMax": "86",
    "horaHrMax": "Varias",
    "hrMin": "44",
    "horaHrMin": "15:10",
    "pintMax": "6,0",
    "horaPIntMax": "13:40"
  },
  {
    "fecha": "2020-03-24",
    "indicativo": "3194U",
    "nombre": "MADRID, CIUDAD UNIVERSITARIA",
    "provincia": "MADRID",
    "altitud": "664",
    "tmed": "12,0",
    "prec": "0,1",
    "tmin": "8,1",
    "horatmin": "07:00",
    "tmax": "15,9",
    "horatmax": "13:00",
    "hrMedia": "54",
    "hrMax": "76",
    "horaHrMax": "06:50",
    "hrMin": "40",
    "horaHrMin": "Varias",
    "pintMax": "0,6",
    "horaPIntMax": "Varias"
  },
  {
    "fecha": "2020-03-25",
    "indicativo": "3194U",
    "nombre": "MADRID, CIUDAD UNIVERSITARIA",
    "provincia": "MADRID",
    "altitud": "664",
    "tmed": "11,2",
    "prec": "0,0",
    "tmin": "5,0",
    "horatmin": "06:50",
    "tmax": "17,4",
    "horatmax": "15:30",
    "hrMedia": "51",
    "hrMax": "75",
    "horaHrMax": "06:50",
    "hrMin": "34",
    "horaHrMin": "18:30",
    "pintMax": "0,0"
  },
  {
    "fecha": "2020-03-26",
    "indicativo": "3194U",
    "nombre": "MADRID, CIUDAD UNIVERSITARIA",
    "provincia": "MADRID",
    "altitud": "664",
    "tmed": "8,7",
    "prec": "0,0",
    "tmin": "0,8",
    "horatmin": "06:20",
    "tmax": "16,6",
    "horatmax": "15:00",
    "hrMedia": "38",
    "hrMax": "70",
    "horaHrMax": "01:10",
    "hrMin": "22",
    "horaHrMin": "13:20",
    "pintMax": "0,0"
  },
  {
    "fecha": "2020-03-27",
    "indicativo": "3194U",
    "nombre": "MADRID, CIUDAD UNIVERSITARIA",
    "provincia": "MADRID",
    "altitud": "664",
    "tmed": "6,6",
    "prec": "0,2",
    "tmin": "2,1",
    "horatmin": "08:50",
    "tmax": "11,0",
    "horatmax": "16:30",
    "hrMedia": "56",
    "hrMax": "82",
    "horaHrMax": "08:50",
    "hrMin": "37",
    "horaHrMin": "00:00",
    "pintMax": "0,6",
    "horaPIntMax": "Varias"
  },
  {
    "fecha": "2020-03-28",
    "indicativo": "3194U",
    "nombre": "MADRID, CIUDAD UNIVERSITARIA",
    "provincia": "MADRID",
    "altitud": "664",
    "tmed": "7,2",
    "prec": "0,0",
    "tmin": "-1,5",
    "horatmin": "06:30",
    "tmax": "16,0",
    "horatmax": "15:40",
    "hrMedia": "44",
    "hrMax": "86",
    "horaHrMax": "Varias",
    "hrMin": "22",
    "horaHrMin": "13:00",
    "pintMax": "0,0"
  },
  {
    "fecha": "2020-03-29",
    "indicativo": "3194U",
    "nombre": "MADRID, CIUDAD UNIVERSITARIA",
    "provincia": "MADRID",
    "altitud": "664",
    "tmed": "10,4",
    "prec": "0,0",
    "tmin": "1,0",
    "horatmin": "06:50",
    "tmax": "19,8",
    "horatmax": "15:30",
    "hrMedia": "44",
    "hrMax": "81",
    "horaHrMax": "06:30",
    "hrMin": "26",
    "horaHrMin": "15:00",
    "pintMax": "0,0"
  },
  {
    "fecha": "2020-03-30",
    "indicativo": "3194U",
    "nombre": "MADRID, CIUDAD UNIVERSITARIA",
    "provincia": "MADRID",
    "altitud": "664",
    "tmed": "5,3",
    "prec": "8,4",
    "tmin": "0,6",
    "horatmin": "23:00",
    "tmax": "10,0",
    "horatmax": "00:10",
    "hrMedia": "64",
    "hrMax": "87",
    "horaHrMax": "Varias",
    "hrMin": "38",
    "horaHrMin": "00:00",
    "pintMax": "1,2",
    "horaPIntMax": "Varias"
  },
  {
    "fecha": "2020-03-31",
    "indicativo": "3194U",
    "nombre": "MADRID, CIUDAD UNIVERSITARIA",
    "provincia": "MADRID",
    "altitud": "664",
    "tmed": "4,8",
    "prec": "16,4",
    "tmin": "0,1",
    "horatmin": "05:40",
    "tmax": "9,5",
    "horatmax": "16:00",
    "hrMedia": "87",
    "hrMax": "87",
    "horaHrMax": "Varias",
    "hrMin": "85",
    "horaHrMin": "Varias",
    "pintMax": "8,4",
    "horaPIntMax": "17:05"
  },
  {
    "fecha": "2020-04-01",
    "indicativo": "3194U",
    "nombre": "MADRID, CIUDAD UNIVERSITARIA",
    "provincia": "MADRID",
    "altitud": "664",
    "tmed": "9,0",
    "prec": "3,7",
    "tmin": "3,3",
    "horatmin": "23:59",
    "tmax": "14,8",
    "horatmax": "15:10",
    "hrMedia": "58",
    "hrMax": "86",
    "horaHrMax": "07:00",
    "hrMin": "38",
    "horaHrMin": "17:00",
    "pintMax": "13,2",
    "horaPIntMax": "09:55"
  },
  {
    "fecha": "2020-04-02",
    "indicativo": "3194U",
    "nombre": "MADRID, CIUDAD UNIVERSITARIA",
    "provincia": "MADRID",
    "altitud": "664",
    "tmed": "7,8",
    "prec": "0,3",
    "tmin": "0,4",
    "horatmin": "04:20",
    "tmax": "15,1",
    "horatmax": "13:40",
    "hrMedia": "63",
    "hrMax": "86",
    "horaHrMax": "Varias",
    "hrMin": "38",
    "horaHrMin": "15:20",
    "pintMax": "0,6",
    "horaPIntMax": "Varias"
  },
  {
    "fecha": "2020-04-03",
    "indicativo": "3194U",
    "nombre": "MADRID, CIUDAD UNIVERSITARIA",
    "provincia": "MADRID",
    "altitud": "664",
    "tmed": "9,6",
    "prec": "0,0",
    "tmin": "1,9",
    "horatmin": "06:30",
    "tmax": "17,2",
    "horatmax": "15:00",
    "hrMedia": "44",
    "hrMax": "82",
    "horaHrMax": "06:40",
    "hrMin": "21",
    "horaHrMin": "18:00",
    "pintMax": "0,0"
  },
  {
    "fecha": "2020-04-04",
    "indicativo": "3194U",
    "nombre": "MADRID, CIUDAD UNIVERSITARIA",
    "provincia": "MADRID",
    "altitud": "664",
    "tmed": "9,7",
    "prec": "0,0",
    "tmin": "1,8",
    "horatmin": "05:00",
    "tmax": "17,6",
    "horatmax": "13:50",
    "hrMedia": "47",
    "hrMax": "81",
    "horaHrMax": "Varias",
    "hrMin": "29",
    "horaHrMin": "14:20",
    "pintMax": "0,0"
  },
  {
    "fecha": "2020-04-05",
    "indicativo": "3194U",
    "nombre": "MADRID, CIUDAD UNIVERSITARIA",
    "provincia": "MADRID",
    "altitud": "664",
    "tmed": "13,8",
    "prec": "0,5",
    "tmin": "8,3",
    "horatmin": "06:30",
    "tmax": "19,4",
    "horatmax": "14:20",
    "hrMedia": "50",
    "hrMax": "71",
    "horaHrMax": "06:30",
    "hrMin": "38",
    "horaHrMin": "16:30",
    "pintMax": "0,6",
    "horaPIntMax": "23:55"
  },
  {
    "fecha": "2020-04-06",
    "indicativo": "3194U",
    "nombre": "MADRID, CIUDAD UNIVERSITARIA",
    "provincia": "MADRID",
    "altitud": "664",
    "tmed": "15,2",
    "prec": "3,4",
    "tmin": "11,8",
    "horatmin": "05:20",
    "tmax": "18,6",
    "horatmax": "14:40",
    "hrMedia": "59",
    "hrMax": "84",
    "horaHrMax": "Varias",
    "hrMin": "44",
    "horaHrMin": "14:40",
    "pintMax": "2,4",
    "horaPIntMax": "23:35"
  },
  {
    "fecha": "2020-04-07",
    "indicativo": "3194U",
    "nombre": "MADRID, CIUDAD UNIVERSITARIA",
    "provincia": "MADRID",
    "altitud": "664",
    "tmed": "13,6",
    "prec": "0,2",
    "tmin": "9,7",
    "horatmin": "04:50",
    "tmax": "17,4",
    "horatmax": "13:40",
    "hrMedia": "67",
    "hrMax": "86",
    "horaHrMax": "Varias",
    "hrMin": "54",
    "horaHrMin": "12:50",
    "pintMax": "1,2",
    "horaPIntMax": "Varias"
  },
  {
    "fecha": "2020-04-08",
    "indicativo": "3194U",
    "nombre": "MADRID, CIUDAD UNIVERSITARIA",
    "provincia": "MADRID",
    "altitud": "664",
    "tmed": "16,3",
    "prec": "0,0",
    "tmin": "11,2",
    "horatmin": "04:30",
    "tmax": "21,4",
    "horatmax": "16:40",
    "hrMedia": "50",
    "hrMax": "84",
    "horaHrMax": "03:10",
    "hrMin": "32",
    "horaHrMin": "16:50",
    "pintMax": "0,0"
  },
  {
    "fecha": "2020-04-09",
    "indicativo": "3194U",
    "nombre": "MADRID, CIUDAD UNIVERSITARIA",
    "provincia": "MADRID",
    "altitud": "664",
    "tmed": "13,2",
    "prec": "8,8",
    "tmin": "11,0",
    "horatmin": "23:40",
    "tmax": "15,3",
    "horatmax": "10:10",
    "hrMedia": "58",
    "hrMax": "83",
    "horaHrMax": "Varias",
    "hrMin": "44",
    "horaHrMin": "10:30",
    "pintMax": "1,8",
    "horaPIntMax": "Varias"
  },
  {
    "fecha": "2020-04-10",
    "indicativo": "3194U",
    "nombre": "MADRID, CIUDAD UNIVERSITARIA",
    "provincia": "MADRID",
    "altitud": "664",
    "tmed": "12,7",
    "prec": "1,6",
    "tmin": "10,1",
    "horatmin": "05:30",
    "tmax": "15,3",
    "horatmax": "16:00",
    "hrMedia": "80",
    "hrMax": "85",
    "horaHrMax": "Varias",
    "hrMin": "67",
    "horaHrMin": "23:50",
    "pintMax": "1,8",
    "horaPIntMax": "01:25"
  },
  {
    "fecha": "2020-04-11",
    "indicativo": "3194U",
    "nombre": "MADRID, CIUDAD UNIVERSITARIA",
    "provincia": "MADRID",
    "altitud": "664",
    "tmed": "14,9",
    "prec": "0,0",
    "tmin": "10,7",
    "horatmin": "03:40",
    "tmax": "19,1",
    "horatmax": "16:10",
    "hrMedia": "55",
    "hrMax": "82",
    "horaHrMax": "Varias",
    "hrMin": "41",
    "horaHrMin": "17:10",
    "pintMax": "0,6",
    "horaPIntMax": "01:35"
  },
  {
    "fecha": "2020-04-12",
    "indicativo": "3194U",
    "nombre": "MADRID, CIUDAD UNIVERSITARIA",
    "provincia": "MADRID",
    "altitud": "664",
    "tmed": "14,8",
    "prec": "0,7",
    "tmin": "10,4",
    "horatmin": "05:00",
    "tmax": "19,3",
    "horatmax": "16:10",
    "hrMedia": "33",
    "hrMax": "58",
    "horaHrMax": "04:40",
    "hrMin": "28",
    "horaHrMin": "18:00",
    "pintMax": "0,0"
  },
  {
    "fecha": "2020-04-13",
    "indicativo": "3194U",
    "nombre": "MADRID, CIUDAD UNIVERSITARIA",
    "provincia": "MADRID",
    "altitud": "664",
    "tmed": "13,3",
    "prec": "1,2",
    "tmin": "7,8",
    "horatmin": "07:50",
    "tmax": "18,8",
    "horatmax": "16:00",
    "hrMedia": "56",
    "hrMax": "79",
    "horaHrMax": "Varias",
    "hrMin": "36",
    "horaHrMin": "16:50",
    "pintMax": "3,0",
    "horaPIntMax": "07:55"
  },
  {
    "fecha": "2020-04-14",
    "indicativo": "3194U",
    "nombre": "MADRID, CIUDAD UNIVERSITARIA",
    "provincia": "MADRID",
    "altitud": "664",
    "tmed": "12,8",
    "prec": "8,7",
    "tmin": "9,0",
    "horatmin": "02:20",
    "tmax": "16,7",
    "horatmax": "14:00",
    "hrMedia": "69",
    "hrMax": "82",
    "horaHrMax": "Varias",
    "hrMin": "53",
    "horaHrMin": "14:40",
    "pintMax": "15,6",
    "horaPIntMax": "15:45"
  },
  {
    "fecha": "2020-04-15",
    "indicativo": "3194U",
    "nombre": "MADRID, CIUDAD UNIVERSITARIA",
    "provincia": "MADRID",
    "altitud": "664",
    "tmed": "12,0",
    "prec": "17,9",
    "tmin": "8,6",
    "horatmin": "08:30",
    "tmax": "15,5",
    "horatmax": "15:00",
    "hrMedia": "67",
    "hrMax": "86",
    "horaHrMax": "09:30",
    "hrMin": "52",
    "horaHrMin": "15:00",
    "pintMax": "19,2",
    "horaPIntMax": "15:45"
  },
  {
    "fecha": "2020-04-16",
    "indicativo": "3194U",
    "nombre": "MADRID, CIUDAD UNIVERSITARIA",
    "provincia": "MADRID",
    "altitud": "664",
    "tmed": "14,3",
    "prec": "3,4",
    "tmin": "10,5",
    "horatmin": "06:00",
    "tmax": "18,1",
    "horatmax": "13:10",
    "hrMedia": "67",
    "hrMax": "85",
    "horaHrMax": "Varias",
    "hrMin": "41",
    "horaHrMin": "13:00",
    "pintMax": "4,2",
    "horaPIntMax": "19:15"
  },
  {
    "fecha": "2020-04-17",
    "indicativo": "3194U",
    "nombre": "MADRID, CIUDAD UNIVERSITARIA",
    "provincia": "MADRID",
    "altitud": "664",
    "tmed": "14,2",
    "prec": "0,1",
    "tmin": "9,9",
    "horatmin": "Varias",
    "tmax": "18,4",
    "horatmax": "13:30",
    "hrMedia": "57",
    "hrMax": "86",
    "horaHrMax": "Varias",
    "hrMin": "39",
    "horaHrMin": "14:10",
    "pintMax": "0,6",
    "horaPIntMax": "07:05"
  },
  {
    "fecha": "2020-04-18",
    "indicativo": "3194U",
    "nombre": "MADRID, CIUDAD UNIVERSITARIA",
    "provincia": "MADRID",
    "altitud": "664",
    "tmed": "14,5",
    "prec": "5,1",
    "tmin": "8,0",
    "horatmin": "06:00",
    "tmax": "21,0",
    "horatmax": "15:10",
    "hrMedia": "52",
    "hrMax": "86",
    "horaHrMax": "Varias",
    "hrMin": "34",
    "horaHrMin": "18:00",
    "pintMax": "0,6",
    "horaPIntMax": "Varias"
  },
  {
    "fecha": "2020-04-19",
    "indicativo": "3194U",
    "nombre": "MADRID, CIUDAD UNIVERSITARIA",
    "provincia": "MADRID",
    "altitud": "664",
    "tmed": "13,6",
    "prec": "4,2",
    "tmin": "8,1",
    "horatmin": "23:59",
    "tmax": "19,0",
    "horatmax": "15:00",
    "hrMedia": "71",
    "hrMax": "85",
    "horaHrMax": "Varias",
    "hrMin": "39",
    "horaHrMin": "15:00",
    "pintMax": "14,4",
    "horaPIntMax": "02:35"
  },
  {
    "fecha": "2020-04-20",
    "indicativo": "3194U",
    "nombre": "MADRID, CIUDAD UNIVERSITARIA",
    "provincia": "MADRID",
    "altitud": "664",
    "tmed": "11,7",
    "prec": "0,1",
    "tmin": "5,1",
    "horatmin": "06:10",
    "tmax": "18,3",
    "horatmax": "13:00",
    "hrMedia": "56",
    "hrMax": "87",
    "horaHrMax": "Varias",
    "hrMin": "39",
    "horaHrMin": "13:00",
    "pintMax": "0,0"
  },
  {
    "fecha": "2020-04-21",
    "indicativo": "3194U",
    "nombre": "MADRID, CIUDAD UNIVERSITARIA",
    "provincia": "MADRID",
    "altitud": "664",
    "tmed": "11,8",
    "prec": "0,0",
    "tmin": "7,6",
    "horatmin": "05:40",
    "tmax": "15,9",
    "horatmax": "17:00",
    "hrMedia": "61",
    "hrMax": "82",
    "horaHrMax": "08:00",
    "hrMin": "44",
    "horaHrMin": "17:10",
    "pintMax": "0,6",
    "horaPIntMax": "02:45"
  },
  {
    "fecha": "2020-04-22",
    "indicativo": "3194U",
    "nombre": "MADRID, CIUDAD UNIVERSITARIA",
    "provincia": "MADRID",
    "altitud": "664",
    "tmed": "14,0",
    "prec": "0,0",
    "tmin": "7,2",
    "horatmin": "06:00",
    "tmax": "20,9",
    "horatmax": "13:50",
    "hrMedia": "54",
    "hrMax": "83",
    "horaHrMax": "06:30",
    "hrMin": "35",
    "horaHrMin": "13:40",
    "pintMax": "0,0"
  },
  {
    "fecha": "2020-04-23",
    "indicativo": "3194U",
    "nombre": "MADRID, CIUDAD UNIVERSITARIA",
    "provincia": "MADRID",
    "altitud": "664",
    "tmed": "15,6",
    "prec": "0,0",
    "tmin": "11,6",
    "horatmin": "02:00",
    "tmax": "19,7",
    "horatmax": "14:40",
    "hrMedia": "54",
    "hrMax": "77",
    "horaHrMax": "05:10",
    "hrMin": "41",
    "horaHrMin": "16:30",
    "pintMax": "0,0"
  },
  {
    "fecha": "2020-04-24",
    "indicativo": "3194U",
    "nombre": "MADRID, CIUDAD UNIVERSITARIA",
    "provincia": "MADRID",
    "altitud": "664",
    "tmed": "16,0",
    "prec": "0,0",
    "tmin": "9,8",
    "horatmin": "06:00",
    "tmax": "22,2",
    "horatmax": "16:00",
    "hrMedia": "50",
    "hrMax": "83",
    "horaHrMax": "Varias",
    "hrMin": "32",
    "horaHrMin": "15:40",
    "pintMax": "0,0"
  },
  {
    "fecha": "2020-04-25",
    "indicativo": "3194U",
    "nombre": "MADRID, CIUDAD UNIVERSITARIA",
    "provincia": "MADRID",
    "altitud": "664",
    "tmed": "16,1",
    "prec": "0,0",
    "tmin": "9,7",
    "horatmin": "06:00",
    "tmax": "22,5",
    "horatmax": "13:50",
    "hrMedia": "48",
    "hrMax": "77",
    "horaHrMax": "06:30",
    "hrMin": "36",
    "horaHrMin": "14:00",
    "pintMax": "0,0"
  },
  {
    "fecha": "2020-04-26",
    "indicativo": "3194U",
    "nombre": "MADRID, CIUDAD UNIVERSITARIA",
    "provincia": "MADRID",
    "altitud": "664",
    "tmed": "15,8",
    "prec": "0,0",
    "tmin": "11,0",
    "horatmin": "05:50",
    "tmax": "20,7",
    "horatmax": "14:20",
    "hrMedia": "55",
    "hrMax": "85",
    "horaHrMax": "Varias",
    "hrMin": "36",
    "horaHrMin": "14:10",
    "pintMax": "0,0"
  },
  {
    "fecha": "2020-04-27",
    "indicativo": "3194U",
    "nombre": "MADRID, CIUDAD UNIVERSITARIA",
    "provincia": "MADRID",
    "altitud": "664",
    "tmed": "13,0",
    "prec": "0,0",
    "tmin": "8,8",
    "horatmin": "23:59",
    "tmax": "17,3",
    "horatmax": "11:40",
    "hrMedia": "54",
    "hrMax": "79",
    "horaHrMax": "05:40",
    "hrMin": "37",
    "horaHrMin": "14:20",
    "pintMax": "0,0"
  },
  {
    "fecha": "2020-04-28",
    "indicativo": "3194U",
    "nombre": "MADRID, CIUDAD UNIVERSITARIA",
    "provincia": "MADRID",
    "altitud": "664",
    "tmed": "12,1",
    "prec": "0,0",
    "tmin": "6,0",
    "horatmin": "05:40",
    "tmax": "18,2",
    "horatmax": "15:40",
    "hrMedia": "54",
    "hrMax": "87",
    "horaHrMax": "06:30",
    "hrMin": "35",
    "horaHrMin": "15:40",
    "pintMax": "0,0"
  },
  {
    "fecha": "2020-04-29",
    "indicativo": "3194U",
    "nombre": "MADRID, CIUDAD UNIVERSITARIA",
    "provincia": "MADRID",
    "altitud": "664",
    "tmed": "12,4",
    "prec": "0,0",
    "tmin": "5,3",
    "horatmin": "05:00",
    "tmax": "19,6",
    "horatmax": "14:50",
    "hrMedia": "50",
    "hrMax": "85",
    "horaHrMax": "05:50",
    "hrMin": "32",
    "horaHrMin": "14:30",
    "pintMax": "0,0"
  },
  {
    "fecha": "2020-04-30",
    "indicativo": "3194U",
    "nombre": "MADRID, CIUDAD UNIVERSITARIA",
    "provincia": "MADRID",
    "altitud": "664",
    "tmed": "15,3",
    "prec": "0,0",
    "tmin": "10,1",
    "horatmin": "06:00",
    "tmax": "20,5",
    "horatmax": "13:30",
    "hrMedia": "55",
    "hrMax": "78",
    "horaHrMax": "01:20",
    "hrMin": "39",
    "horaHrMin": "Varias",
    "pintMax": "0,0"
  },
  {
    "fecha": "2020-05-01",
    "indicativo": "3194U",
    "nombre": "MADRID, CIUDAD UNIVERSITARIA",
    "provincia": "MADRID",
    "altitud": "664",
    "tmed": "16,4",
    "prec": "0,0",
    "tmin": "10,0",
    "horatmin": "04:50",
    "tmax": "22,7",
    "horatmax": "16:00",
    "hrMedia": "59",
    "hrMax": "83",
    "horaHrMax": "Varias",
    "hrMin": "42",
    "horaHrMin": "15:50",
    "pintMax": "0,0"
  },
  {
    "fecha": "2020-05-02",
    "indicativo": "3194U",
    "nombre": "MADRID, CIUDAD UNIVERSITARIA",
    "provincia": "MADRID",
    "altitud": "664",
    "tmed": "18,8",
    "prec": "0,0",
    "tmin": "11,0",
    "horatmin": "05:00",
    "tmax": "26,5",
    "horatmax": "15:00",
    "hrMedia": "49",
    "hrMax": "86",
    "horaHrMax": "Varias",
    "hrMin": "28",
    "horaHrMin": "18:00",
    "pintMax": "0,0"
  },
  {
    "fecha": "2020-05-03",
    "indicativo": "3194U",
    "nombre": "MADRID, CIUDAD UNIVERSITARIA",
    "provincia": "MADRID",
    "altitud": "664",
    "tmed": "19,4",
    "prec": "0,0",
    "tmin": "9,5",
    "horatmin": "05:50",
    "tmax": "29,2",
    "horatmax": "16:30",
    "hrMedia": "45",
    "hrMax": "84",
    "horaHrMax": "Varias",
    "hrMin": "23",
    "horaHrMin": "16:50",
    "pintMax": "0,0"
  },
  {
    "fecha": "2020-05-04",
    "indicativo": "3194U",
    "nombre": "MADRID, CIUDAD UNIVERSITARIA",
    "provincia": "MADRID",
    "altitud": "664",
    "tmed": "22,3",
    "prec": "0,0",
    "tmin": "13,2",
    "horatmin": "05:00",
    "tmax": "31,4",
    "horatmax": "16:00",
    "hrMedia": "38",
    "hrMax": "71",
    "horaHrMax": "02:20",
    "hrMin": "24",
    "horaHrMin": "15:30",
    "pintMax": "0,0"
  },
  {
    "fecha": "2020-05-05",
    "indicativo": "3194U",
    "nombre": "MADRID, CIUDAD UNIVERSITARIA",
    "provincia": "MADRID",
    "altitud": "664",
    "tmed": "17,8",
    "prec": "0,0",
    "tmin": "10,6",
    "horatmin": "23:59",
    "tmax": "25,0",
    "horatmax": "15:20",
    "hrMedia": "34",
    "hrMax": "64",
    "horaHrMax": "04:40",
    "hrMin": "19",
    "horaHrMin": "15:40",
    "pintMax": "0,0"
  },
  {
    "fecha": "2020-05-06",
    "indicativo": "3194U",
    "nombre": "MADRID, CIUDAD UNIVERSITARIA",
    "provincia": "MADRID",
    "altitud": "664",
    "tmed": "15,9",
    "prec": "0,0",
    "tmin": "5,8",
    "horatmin": "05:00",
    "tmax": "26,0",
    "horatmax": "14:10",
    "hrMedia": "37",
    "hrMax": "72",
    "horaHrMax": "06:00",
    "hrMin": "21",
    "horaHrMin": "Varias",
    "pintMax": "0,0"
  },
  {
    "fecha": "2020-05-07",
    "indicativo": "3194U",
    "nombre": "MADRID, CIUDAD UNIVERSITARIA",
    "provincia": "MADRID",
    "altitud": "664",
    "tmed": "19,0",
    "prec": "0,0",
    "tmin": "11,7",
    "horatmin": "02:00",
    "tmax": "26,3",
    "horatmax": "14:00",
    "hrMedia": "37",
    "hrMax": "60",
    "horaHrMax": "01:40",
    "hrMin": "30",
    "horaHrMin": "18:00",
    "pintMax": "0,0"
  },
  {
    "fecha": "2020-05-08",
    "indicativo": "3194U",
    "nombre": "MADRID, CIUDAD UNIVERSITARIA",
    "provincia": "MADRID",
    "altitud": "664",
    "tmed": "21,2",
    "prec": "0,0",
    "tmin": "14,1",
    "horatmin": "04:50",
    "tmax": "28,4",
    "horatmax": "17:00",
    "hrMedia": "36",
    "hrMax": "57",
    "horaHrMax": "02:50",
    "hrMin": "29",
    "horaHrMin": "Varias",
    "pintMax": "0,0"
  },
  {
    "fecha": "2020-05-09",
    "indicativo": "3194U",
    "nombre": "MADRID, CIUDAD UNIVERSITARIA",
    "provincia": "MADRID",
    "altitud": "664",
    "tmed": "18,3",
    "prec": "0,3",
    "tmin": "12,1",
    "horatmin": "Varias",
    "tmax": "24,5",
    "horatmax": "15:20",
    "hrMedia": "47",
    "hrMax": "77",
    "horaHrMax": "06:00",
    "hrMin": "30",
    "horaHrMin": "16:40",
    "pintMax": "0,6",
    "horaPIntMax": "21:45"
  },
  {
    "fecha": "2020-05-10",
    "indicativo": "3194U",
    "nombre": "MADRID, CIUDAD UNIVERSITARIA",
    "provincia": "MADRID",
    "altitud": "664",
    "tmed": "15,4",
    "prec": "0,0",
    "tmin": "9,4",
    "horatmin": "06:00",
    "tmax": "21,3",
    "horatmax": "13:10",
    "hrMedia": "48",
    "hrMax": "83",
    "horaHrMax": "Varias",
    "hrMin": "31",
    "horaHrMin": "13:10",
    "pintMax": "0,6",
    "horaPIntMax": "Varias"
  },
  {
    "fecha": "2020-05-11",
    "indicativo": "3194U",
    "nombre": "MADRID, CIUDAD UNIVERSITARIA",
    "provincia": "MADRID",
    "altitud": "664",
    "tmed": "15,0",
    "prec": "0,0",
    "tmin": "9,5",
    "horatmin": "04:40",
    "tmax": "20,5",
    "horatmax": "16:30",
    "hrMedia": "52",
    "hrMax": "83",
    "horaHrMax": "Varias",
    "hrMin": "37",
    "horaHrMin": "12:30",
    "pintMax": "0,0"
  },
  {
    "fecha": "2020-05-12",
    "indicativo": "3194U",
    "nombre": "MADRID, CIUDAD UNIVERSITARIA",
    "provincia": "MADRID",
    "altitud": "664",
    "tmed": "12,4",
    "prec": "9,0",
    "tmin": "9,3",
    "horatmin": "23:59",
    "tmax": "15,6",
    "horatmax": "12:10",
    "hrMedia": "77",
    "hrMax": "87",
    "horaHrMax": "Varias",
    "hrMin": "57",
    "horaHrMin": "12:10",
    "pintMax": "4,8",
    "horaPIntMax": "22:35"
  },
  {
    "fecha": "2020-05-13",
    "indicativo": "3194U",
    "nombre": "MADRID, CIUDAD UNIVERSITARIA",
    "provincia": "MADRID",
    "altitud": "664",
    "tmed": "13,8",
    "prec": "2,8",
    "tmin": "9,1",
    "horatmin": "01:00",
    "tmax": "18,6",
    "horatmax": "14:50",
    "hrMedia": "55",
    "hrMax": "87",
    "horaHrMax": "Varias",
    "hrMin": "36",
    "horaHrMin": "14:30",
    "pintMax": "0,6",
    "horaPIntMax": "00:05"
  },
  {
    "fecha": "2020-05-14",
    "indicativo": "3194U",
    "nombre": "MADRID, CIUDAD UNIVERSITARIA",
    "provincia": "MADRID",
    "altitud": "664",
    "tmed": "12,2",
    "prec": "3,3",
    "tmin": "9,2",
    "horatmin": "07:30",
    "tmax": "15,2",
    "horatmax": "15:30",
    "hrMedia": "66",
    "hrMax": "85",
    "horaHrMax": "Varias",
    "hrMin": "43",
    "horaHrMin": "16:10",
    "pintMax": "2,4",
    "horaPIntMax": "05:25"
  },
  {
    "fecha": "2020-05-15",
    "indicativo": "3194U",
    "nombre": "MADRID, CIUDAD UNIVERSITARIA",
    "provincia": "MADRID",
    "altitud": "664",
    "tmed": "13,8",
    "prec": "13,6",
    "tmin": "8,7",
    "horatmin": "05:00",
    "tmax": "19,0",
    "horatmax": "12:30",
    "hrMedia": "68",
    "hrMax": "86",
    "horaHrMax": "06:10",
    "hrMin": "35",
    "horaHrMin": "13:00",
    "pintMax": "31,8",
    "horaPIntMax": "14:35"
  },
  {
    "fecha": "2020-05-16",
    "indicativo": "3194U",
    "nombre": "MADRID, CIUDAD UNIVERSITARIA",
    "provincia": "MADRID",
    "altitud": "664",
    "tmed": "15,2",
    "prec": "0,0",
    "tmin": "10,2",
    "horatmin": "Varias",
    "tmax": "20,2",
    "horatmax": "12:50",
    "hrMedia": "51",
    "hrMax": "85",
    "horaHrMax": "Varias",
    "hrMin": "35",
    "horaHrMin": "13:00",
    "pintMax": "0,0"
  },
  {
    "fecha": "2020-05-17",
    "indicativo": "3194U",
    "nombre": "MADRID, CIUDAD UNIVERSITARIA",
    "provincia": "MADRID",
    "altitud": "664",
    "tmed": "15,2",
    "prec": "0,0",
    "tmin": "7,9",
    "horatmin": "05:30",
    "tmax": "22,6",
    "horatmax": "16:50",
    "hrMedia": "37",
    "hrMax": "70",
    "horaHrMax": "05:20",
    "hrMin": "28",
    "horaHrMin": "18:00",
    "pintMax": "0,0"
  },
  {
    "fecha": "2020-05-18",
    "indicativo": "3194U",
    "nombre": "MADRID, CIUDAD UNIVERSITARIA",
    "provincia": "MADRID",
    "altitud": "664",
    "tmed": "18,2",
    "prec": "0,0",
    "tmin": "7,8",
    "horatmin": "05:50",
    "tmax": "28,5",
    "horatmax": "16:30",
    "hrMedia": "37",
    "hrMax": "82",
    "horaHrMax": "05:50",
    "hrMin": "19",
    "horaHrMin": "13:00",
    "pintMax": "0,0"
  },
  {
    "fecha": "2020-05-19",
    "indicativo": "3194U",
    "nombre": "MADRID, CIUDAD UNIVERSITARIA",
    "provincia": "MADRID",
    "altitud": "664",
    "tmed": "19,6",
    "prec": "0,0",
    "tmin": "9,2",
    "horatmin": "05:30",
    "tmax": "30,1",
    "horatmax": "15:20",
    "hrMedia": "35",
    "hrMax": "78",
    "horaHrMax": "06:00",
    "hrMin": "19",
    "horaHrMin": "13:00",
    "pintMax": "0,0"
  },
  {
    "fecha": "2020-05-20",
    "indicativo": "3194U",
    "nombre": "MADRID, CIUDAD UNIVERSITARIA",
    "provincia": "MADRID",
    "altitud": "664",
    "tmed": "21,8",
    "prec": "0,0",
    "tmin": "11,0",
    "horatmin": "05:30",
    "tmax": "32,5",
    "horatmax": "16:00",
    "hrMedia": "32",
    "hrMax": "77",
    "horaHrMax": "05:30",
    "hrMin": "15",
    "horaHrMin": "15:30",
    "pintMax": "0,0"
  },
  {
    "fecha": "2020-05-21",
    "indicativo": "3194U",
    "nombre": "MADRID, CIUDAD UNIVERSITARIA",
    "provincia": "MADRID",
    "altitud": "664",
    "tmed": "21,6",
    "prec": "0,0",
    "tmin": "10,7",
    "horatmin": "06:00",
    "tmax": "32,6",
    "horatmax": "16:00",
    "hrMedia": "32",
    "hrMax": "71",
    "horaHrMax": "06:00",
    "hrMin": "18",
    "horaHrMin": "Varias",
    "pintMax": "0,0"
  },
  {
    "fecha": "2020-05-22",
    "indicativo": "3194U",
    "nombre": "MADRID, CIUDAD UNIVERSITARIA",
    "provincia": "MADRID",
    "altitud": "664",
    "tmed": "23,0",
    "prec": "0,0",
    "tmin": "12,9",
    "horatmin": "05:00",
    "tmax": "33,2",
    "horatmax": "15:50",
    "hrMedia": "36",
    "hrMax": "77",
    "horaHrMax": "05:30",
    "hrMin": "22",
    "horaHrMin": "18:00",
    "pintMax": "0,0"
  },
  {
    "fecha": "2020-05-23",
    "indicativo": "3194U",
    "nombre": "MADRID, CIUDAD UNIVERSITARIA",
    "provincia": "MADRID",
    "altitud": "664",
    "tmed": "24,2",
    "prec": "0,0",
    "tmin": "14,6",
    "horatmin": "05:40",
    "tmax": "33,7",
    "horatmax": "16:30",
    "hrMedia": "35",
    "hrMax": "73",
    "horaHrMax": "05:40",
    "hrMin": "22",
    "horaHrMin": "Varias",
    "pintMax": "0,0"
  },
  {
    "fecha": "2020-05-24",
    "indicativo": "3194U",
    "nombre": "MADRID, CIUDAD UNIVERSITARIA",
    "provincia": "MADRID",
    "altitud": "664",
    "tmed": "24,0",
    "prec": "0,0",
    "tmin": "16,5",
    "horatmin": "04:30",
    "tmax": "31,6",
    "horatmax": "16:30",
    "hrMedia": "38",
    "hrMax": "63",
    "horaHrMax": "04:20",
    "hrMin": "29",
    "horaHrMin": "17:10",
    "pintMax": "0,0"
  },
  {
    "fecha": "2020-05-25",
    "indicativo": "3194U",
    "nombre": "MADRID, CIUDAD UNIVERSITARIA",
    "provincia": "MADRID",
    "altitud": "664",
    "tmed": "23,4",
    "prec": "0,0",
    "tmin": "16,1",
    "horatmin": "23:50",
    "tmax": "30,7",
    "horatmax": "14:10",
    "hrMedia": "49",
    "hrMax": "72",
    "horaHrMax": "06:10",
    "hrMin": "33",
    "horaHrMin": "13:40",
    "pintMax": "0,0"
  },
  {
    "fecha": "2020-05-26",
    "indicativo": "3194U",
    "nombre": "MADRID, CIUDAD UNIVERSITARIA",
    "provincia": "MADRID",
    "altitud": "664",
    "tmed": "21,3",
    "prec": "0,0",
    "tmin": "16,3",
    "horatmin": "00:10",
    "tmax": "26,3",
    "horatmax": "13:30",
    "hrMedia": "48",
    "hrMax": "76",
    "horaHrMax": "Varias",
    "hrMin": "40",
    "horaHrMin": "13:30",
    "pintMax": "0,0"
  },
  {
    "fecha": "2020-05-27",
    "indicativo": "3194U",
    "nombre": "MADRID, CIUDAD UNIVERSITARIA",
    "provincia": "MADRID",
    "altitud": "664",
    "tmed": "22,6",
    "prec": "0,0",
    "tmin": "15,1",
    "horatmin": "05:30",
    "tmax": "30,2",
    "horatmax": "15:40",
    "hrMedia": "32",
    "hrMax": "76",
    "horaHrMax": "05:10",
    "hrMin": "25",
    "horaHrMin": "18:00",
    "pintMax": "0,0"
  },
  {
    "fecha": "2020-05-28",
    "indicativo": "3194U",
    "nombre": "MADRID, CIUDAD UNIVERSITARIA",
    "provincia": "MADRID",
    "altitud": "664",
    "tmed": "22,6",
    "prec": "0,0",
    "tmin": "16,2",
    "horatmin": "05:50",
    "tmax": "29,1",
    "horatmax": "16:20",
    "hrMedia": "29",
    "hrMax": "47",
    "horaHrMax": "02:20",
    "hrMin": "24",
    "horaHrMin": "15:20",
    "pintMax": "0,0"
  },
  {
    "fecha": "2020-05-29",
    "indicativo": "3194U",
    "nombre": "MADRID, CIUDAD UNIVERSITARIA",
    "provincia": "MADRID",
    "altitud": "664",
    "tmed": "23,4",
    "prec": "0,0",
    "tmin": "15,4",
    "horatmin": "06:00",
    "tmax": "31,5",
    "horatmax": "15:00",
    "hrMedia": "32",
    "hrMax": "54",
    "horaHrMax": "06:30",
    "hrMin": "23",
    "horaHrMin": "18:00",
    "pintMax": "0,0"
  },
  {
    "fecha": "2020-05-30",
    "indicativo": "3194U",
    "nombre": "MADRID, CIUDAD UNIVERSITARIA",
    "provincia": "MADRID",
    "altitud": "664",
    "tmed": "24,9",
    "prec": "0,0",
    "tmin": "16,9",
    "horatmin": "04:00",
    "tmax": "32,9",
    "horatmax": "16:20",
    "hrMedia": "31",
    "hrMax": "52",
    "horaHrMax": "03:40",
    "hrMin": "23",
    "horaHrMin": "16:20",
    "pintMax": "0,0"
  },
  {
    "fecha": "2020-05-31",
    "indicativo": "3194U",
    "nombre": "MADRID, CIUDAD UNIVERSITARIA",
    "provincia": "MADRID",
    "altitud": "664",
    "tmed": "24,0",
    "prec": "13,1",
    "tmin": "15,7",
    "horatmin": "21:30",
    "tmax": "32,2",
    "horatmax": "14:50",
    "hrMedia": "52",
    "hrMax": "84",
    "horaHrMax": "Varias",
    "hrMin": "29",
    "horaHrMin": "Varias",
    "pintMax": "41,4",
    "horaPIntMax": "17:25"
  },
  {
    "fecha": "2020-06-01",
    "indicativo": "3194U",
    "nombre": "MADRID, CIUDAD UNIVERSITARIA",
    "provincia": "MADRID",
    "altitud": "664",
    "tmed": "20,8",
    "prec": "0,0",
    "tmin": "13,5",
    "horatmin": "05:00",
    "tmax": "28,2",
    "horatmax": "14:20",
    "hrMedia": "46",
    "hrMax": "86",
    "horaHrMax": "05:30",
    "hrMin": "27",
    "horaHrMin": "16:30",
    "pintMax": "0,0"
  },
  {
    "fecha": "2020-06-02",
    "indicativo": "3194U",
    "nombre": "MADRID, CIUDAD UNIVERSITARIA",
    "provincia": "MADRID",
    "altitud": "664",
    "tmed": "23,1",
    "prec": "0,0",
    "tmin": "15,2",
    "horatmin": "05:30",
    "tmax": "31,0",
    "horatmax": "16:10",
    "hrMedia": "34",
    "hrMax": "75",
    "horaHrMax": "05:30",
    "hrMin": "19",
    "horaHrMin": "18:00",
    "pintMax": "0,0"
  },
  {
    "fecha": "2020-06-03",
    "indicativo": "3194U",
    "nombre": "MADRID, CIUDAD UNIVERSITARIA",
    "provincia": "MADRID",
    "altitud": "664",
    "tmed": "22,0",
    "prec": "1,1",
    "tmin": "13,8",
    "horatmin": "05:30",
    "tmax": "30,2",
    "horatmax": "14:40",
    "hrMedia": "37",
    "hrMax": "70",
    "horaHrMax": "23:59",
    "hrMin": "29",
    "horaHrMin": "12:30",
    "pintMax": "0,6",
    "horaPIntMax": "20:45"
  },
  {
    "fecha": "2020-06-04",
    "indicativo": "3194U",
    "nombre": "MADRID, CIUDAD UNIVERSITARIA",
    "provincia": "MADRID",
    "altitud": "664",
    "tmed": "18,8",
    "prec": "0,0",
    "tmin": "12,5",
    "horatmin": "23:50",
    "tmax": "25,2",
    "horatmax": "14:20",
    "hrMedia": "45",
    "hrMax": "82",
    "horaHrMax": "06:50",
    "hrMin": "24",
    "horaHrMin": "Varias",
    "pintMax": "1,2",
    "horaPIntMax": "Varias"
  },
  {
    "fecha": "2020-06-05",
    "indicativo": "3194U",
    "nombre": "MADRID, CIUDAD UNIVERSITARIA",
    "provincia": "MADRID",
    "altitud": "664",
    "tmed": "19,6",
    "prec": "0,0",
    "tmin": "9,9",
    "horatmin": "06:00",
    "tmax": "29,4",
    "horatmax": "15:40",
    "hrMedia": "34",
    "hrMax": "74",
    "horaHrMax": "06:00",
    "hrMin": "22",
    "horaHrMin": "15:50",
    "pintMax": "0,0"
  },
  {
    "fecha": "2020-06-06",
    "indicativo": "3194U",
    "nombre": "MADRID, CIUDAD UNIVERSITARIA",
    "provincia": "MADRID",
    "altitud": "664",
    "tmed": "21,8",
    "prec": "0,0",
    "tmin": "14,9",
    "horatmin": "05:00",
    "tmax": "28,7",
    "horatmax": "15:50",
    "hrMedia": "34",
    "hrMax": "61",
    "horaHrMax": "06:00",
    "hrMin": "25",
    "horaHrMin": "16:00",
    "pintMax": "0,0"
  },
  {
    "fecha": "2020-06-07",
    "indicativo": "3194U",
    "nombre": "MADRID, CIUDAD UNIVERSITARIA",
    "provincia": "MADRID",
    "altitud": "664",
    "tmed": "19,8",
    "prec": "1,7",
    "tmin": "12,5",
    "horatmin": "23:59",
    "tmax": "27,1",
    "horatmax": "15:00",
    "hrMedia": "57",
    "hrMax": "76",
    "horaHrMax": "18:40",
    "hrMin": "33",
    "horaHrMin": "Varias",
    "pintMax": "3,6",
    "horaPIntMax": "17:40"
  },
  {
    "fecha": "2020-06-08",
    "indicativo": "3194U",
    "nombre": "MADRID, CIUDAD UNIVERSITARIA",
    "provincia": "MADRID",
    "altitud": "664",
    "tmed": "17,2",
    "prec": "0,0",
    "tmin": "10,4",
    "horatmin": "04:50",
    "tmax": "24,0",
    "horatmax": "14:50",
    "hrMedia": "34",
    "hrMax": "64",
    "horaHrMax": "00:00",
    "hrMin": "26",
    "horaHrMin": "14:50",
    "pintMax": "0,0"
  },
  {
    "fecha": "2020-06-09",
    "indicativo": "3194U",
    "nombre": "MADRID, CIUDAD UNIVERSITARIA",
    "provincia": "MADRID",
    "altitud": "664",
    "tmed": "17,8",
    "prec": "0,0",
    "tmin": "9,1",
    "horatmin": "05:40",
    "tmax": "26,4",
    "horatmax": "14:40",
    "hrMedia": "32",
    "hrMax": "61",
    "horaHrMax": "05:50",
    "hrMin": "20",
    "horaHrMin": "13:50",
    "pintMax": "0,0"
  },
  {
    "fecha": "2020-06-10",
    "indicativo": "3194U",
    "nombre": "MADRID, CIUDAD UNIVERSITARIA",
    "provincia": "MADRID",
    "altitud": "664",
    "tmed": "18,2",
    "prec": "0,0",
    "tmin": "8,9",
    "horatmin": "05:40",
    "tmax": "27,5",
    "horatmax": "15:00",
    "hrMedia": "33",
    "hrMax": "66",
    "horaHrMax": "05:30",
    "hrMin": "25",
    "horaHrMin": "18:00",
    "pintMax": "0,0"
  },
  {
    "fecha": "2020-06-11",
    "indicativo": "3194U",
    "nombre": "MADRID, CIUDAD UNIVERSITARIA",
    "provincia": "MADRID",
    "altitud": "664",
    "tmed": "19,4",
    "prec": "0,0",
    "tmin": "13,5",
    "horatmin": "03:00",
    "tmax": "25,2",
    "horatmax": "12:00",
    "hrMedia": "39",
    "hrMax": "60",
    "horaHrMax": "19:50",
    "hrMin": "33",
    "horaHrMin": "17:10",
    "pintMax": "0,0"
  },
  {
    "fecha": "2020-06-12",
    "indicativo": "3194U",
    "nombre": "MADRID, CIUDAD UNIVERSITARIA",
    "provincia": "MADRID",
    "altitud": "664",
    "tmed": "15,2",
    "prec": "2,3",
    "tmin": "8,4",
    "horatmin": "05:00",
    "tmax": "21,9",
    "horatmax": "15:30",
    "hrMedia": "42",
    "hrMax": "84",
    "horaHrMax": "21:40",
    "hrMin": "35",
    "horaHrMin": "13:00",
    "pintMax": "5,4",
    "horaPIntMax": "20:35"
  },
  {
    "fecha": "2020-06-13",
    "indicativo": "3194U",
    "nombre": "MADRID, CIUDAD UNIVERSITARIA",
    "provincia": "MADRID",
    "altitud": "664",
    "tmed": "16,8",
    "prec": "0,0",
    "tmin": "8,8",
    "horatmin": "05:40",
    "tmax": "24,9",
    "horatmax": "15:40",
    "hrMedia": "44",
    "hrMax": "85",
    "horaHrMax": "05:30",
    "hrMin": "24",
    "horaHrMin": "15:40",
    "pintMax": "0,0"
  },
  {
    "fecha": "2020-06-14",
    "indicativo": "3194U",
    "nombre": "MADRID, CIUDAD UNIVERSITARIA",
    "provincia": "MADRID",
    "altitud": "664",
    "tmed": "18,6",
    "prec": "0,0",
    "tmin": "10,0",
    "horatmin": "05:00",
    "tmax": "27,2",
    "horatmax": "14:40",
    "hrMedia": "35",
    "hrMax": "70",
    "horaHrMax": "05:10",
    "hrMin": "24",
    "horaHrMin": "Varias",
    "pintMax": "0,0"
  },
  {
    "fecha": "2020-06-15",
    "indicativo": "3194U",
    "nombre": "MADRID, CIUDAD UNIVERSITARIA",
    "provincia": "MADRID",
    "altitud": "664",
    "tmed": "20,1",
    "prec": "0,0",
    "tmin": "11,8",
    "horatmin": "05:40",
    "tmax": "28,4",
    "horatmax": "15:40",
    "hrMedia": "33",
    "hrMax": "64",
    "horaHrMax": "05:40",
    "hrMin": "25",
    "horaHrMin": "13:00",
    "pintMax": "0,0"
  },
  {
    "fecha": "2020-06-18",
    "indicativo": "3194U",
    "nombre": "MADRID, CIUDAD UNIVERSITARIA",
    "provincia": "MADRID",
    "altitud": "664",
    "tmed": "21,4",
    "prec": "0,0",
    "tmin": "12,6",
    "horatmin": "05:30",
    "tmax": "30,2",
    "horatmax": "13:50",
    "hrMedia": "32",
    "hrMax": "64",
    "horaHrMax": "05:30",
    "hrMin": "22",
    "horaHrMin": "18:00",
    "pintMax": "0,0"
  },
  {
    "fecha": "2020-06-19",
    "indicativo": "3194U",
    "nombre": "MADRID, CIUDAD UNIVERSITARIA",
    "provincia": "MADRID",
    "altitud": "664",
    "tmed": "23,0",
    "prec": "0,0",
    "tmin": "14,4",
    "horatmin": "05:00",
    "tmax": "31,7",
    "horatmax": "16:20",
    "hrMedia": "37",
    "hrMax": "67",
    "horaHrMax": "05:40",
    "hrMin": "21",
    "horaHrMin": "16:20",
    "pintMax": "0,0"
  },
  {
    "fecha": "2020-06-20",
    "indicativo": "3194U",
    "nombre": "MADRID, CIUDAD UNIVERSITARIA",
    "provincia": "MADRID",
    "altitud": "664",
    "tmed": "23,3",
    "prec": "0,0",
    "tmin": "13,0",
    "horatmin": "05:50",
    "tmax": "33,6",
    "horatmax": "14:40",
    "hrMedia": "28",
    "hrMax": "55",
    "horaHrMax": "06:00",
    "hrMin": "19",
    "horaHrMin": "18:00",
    "pintMax": "0,0"
  },
  {
    "fecha": "2020-06-21",
    "indicativo": "3194U",
    "nombre": "MADRID, CIUDAD UNIVERSITARIA",
    "provincia": "MADRID",
    "altitud": "664",
    "tmed": "25,2",
    "prec": "0,0",
    "tmin": "15,2",
    "horatmin": "05:50",
    "tmax": "35,3",
    "horatmax": "15:40",
    "hrMedia": "28",
    "hrMax": "52",
    "horaHrMax": "05:50",
    "hrMin": "20",
    "horaHrMin": "18:00",
    "pintMax": "0,0"
  },
  {
    "fecha": "2020-06-22",
    "indicativo": "3194U",
    "nombre": "MADRID, CIUDAD UNIVERSITARIA",
    "provincia": "MADRID",
    "altitud": "664",
    "tmed": "27,4",
    "prec": "0,0",
    "tmin": "18,6",
    "horatmin": "04:50",
    "tmax": "36,3",
    "horatmax": "16:00",
    "hrMedia": "30",
    "hrMax": "49",
    "horaHrMax": "Varias",
    "hrMin": "20",
    "horaHrMin": "18:00",
    "pintMax": "0,0"
  },
  {
    "fecha": "2020-06-23",
    "indicativo": "3194U",
    "nombre": "MADRID, CIUDAD UNIVERSITARIA",
    "provincia": "MADRID",
    "altitud": "664",
    "tmed": "29,2",
    "prec": "0,0",
    "tmin": "21,0",
    "horatmin": "04:20",
    "tmax": "37,3",
    "horatmax": "16:00",
    "hrMedia": "29",
    "hrMax": "46",
    "horaHrMax": "05:30",
    "hrMin": "18",
    "horaHrMin": "18:00",
    "pintMax": "0,0"
  },
  {
    "fecha": "2020-06-24",
    "indicativo": "3194U",
    "nombre": "MADRID, CIUDAD UNIVERSITARIA",
    "provincia": "MADRID",
    "altitud": "664",
    "tmed": "26,5",
    "prec": "0,0",
    "tmin": "20,8",
    "horatmin": "05:30",
    "tmax": "32,2",
    "horatmax": "16:40",
    "hrMedia": "36",
    "hrMax": "48",
    "horaHrMax": "05:50",
    "hrMin": "27",
    "horaHrMin": "18:00",
    "pintMax": "0,0"
  },
  {
    "fecha": "2020-06-25",
    "indicativo": "3194U",
    "nombre": "MADRID, CIUDAD UNIVERSITARIA",
    "provincia": "MADRID",
    "altitud": "664",
    "tmed": "27,6",
    "prec": "0,0",
    "tmin": "19,6",
    "horatmin": "05:30",
    "tmax": "35,6",
    "horatmax": "14:30",
    "hrMedia": "33",
    "hrMax": "51",
    "horaHrMax": "Varias",
    "hrMin": "25",
    "horaHrMin": "18:00",
    "pintMax": "0,0"
  },
  {
    "fecha": "2020-06-26",
    "indicativo": "3194U",
    "nombre": "MADRID, CIUDAD UNIVERSITARIA",
    "provincia": "MADRID",
    "altitud": "664",
    "tmed": "25,8",
    "prec": "0,0",
    "tmin": "19,0",
    "horatmin": "04:00",
    "tmax": "32,7",
    "horatmax": "15:20",
    "hrMedia": "31",
    "hrMax": "58",
    "horaHrMax": "03:40",
    "hrMin": "22",
    "horaHrMin": "18:00",
    "pintMax": "0,0"
  },
  {
    "fecha": "2020-06-27",
    "indicativo": "3194U",
    "nombre": "MADRID, CIUDAD UNIVERSITARIA",
    "provincia": "MADRID",
    "altitud": "664",
    "tmed": "24,8",
    "prec": "0,0",
    "tmin": "15,7",
    "horatmin": "05:40",
    "tmax": "33,9",
    "horatmax": "16:20",
    "hrMedia": "34",
    "hrMax": "55",
    "horaHrMax": "Varias",
    "hrMin": "28",
    "horaHrMin": "Varias",
    "pintMax": "0,0"
  },
  {
    "fecha": "2020-06-28",
    "indicativo": "3194U",
    "nombre": "MADRID, CIUDAD UNIVERSITARIA",
    "provincia": "MADRID",
    "altitud": "664",
    "tmed": "26,8",
    "prec": "0,0",
    "tmin": "17,4",
    "horatmin": "05:00",
    "tmax": "36,2",
    "horatmax": "16:00",
    "hrMedia": "35",
    "hrMax": "62",
    "horaHrMax": "06:10",
    "hrMin": "24",
    "horaHrMin": "Varias",
    "pintMax": "0,0"
  },
  {
    "fecha": "2020-06-29",
    "indicativo": "3194U",
    "nombre": "MADRID, CIUDAD UNIVERSITARIA",
    "provincia": "MADRID",
    "altitud": "664",
    "tmed": "27,6",
    "prec": "0,0",
    "tmin": "17,4",
    "horatmin": "06:00",
    "tmax": "37,9",
    "horatmax": "14:50",
    "hrMedia": "31",
    "hrMax": "61",
    "horaHrMax": "06:00",
    "hrMin": "18",
    "horaHrMin": "16:00",
    "pintMax": "0,0"
  },
  {
    "fecha": "2020-06-30",
    "indicativo": "3194U",
    "nombre": "MADRID, CIUDAD UNIVERSITARIA",
    "provincia": "MADRID",
    "altitud": "664",
    "tmed": "30,4",
    "prec": "0,0",
    "tmin": "22,0",
    "horatmin": "03:50",
    "tmax": "38,7",
    "horatmax": "16:30",
    "hrMedia": "32",
    "hrMax": "55",
    "horaHrMax": "Varias",
    "hrMin": "20",
    "horaHrMin": "14:40",
    "pintMax": "0,0"
  }
]